{
  "schema_version": "1",
  "kind": "deck_text_blob",
  "generated_at": "2026-03-30T05:10:22Z",
  "format": "standard",
  "source": "mtggoldfish",
  "deck_id": "7707537",
  "deck_name": "standard-dimir-excruciator-woe",
  "deck_text": "1 Archenemy's Charm\n2 Bitter Triumph\n1 Cavern of Souls\n2 Day of Black Sun\n4 Gloomlake Verge\n4 Deceit\n3 Doomsday Excruciator\n10 Swamp\n2 Harvester of Misery\n2 Insatiable Avarice\n4 Restless Reef\n1 Malboro\n4 Requiting Hex\n2 Undercity Sewers\n1 Shoot the Sheriff\n4 Stock Up\n4 Superior Spider-Man\n1 Duress\n4 Watery Grave\n2 Winternight Stories\n2 Deadly Cover-Up\nsideboard\n1 Annul\n1 Cruelclaw's Heist\n1 Duress\n1 Flashfreeze\n2 Intimidation Tactics\n2 Oildeep Gearhulk\n1 Overlord of the Balemurk\n2 Quantum Riddler\n1 Soul-Guide Lantern\n1 Strategic Betrayal\n1 Duress\n1 Flashfreeze\n"
}