{
  "schema_version": "1",
  "kind": "deck_text_blob",
  "generated_at": "2026-03-24T17:38:28Z",
  "format": "pauper",
  "source": "mtggoldfish",
  "deck_id": "7696018",
  "deck_name": "pauper-white-aggro",
  "deck_text": "4 Thraben Inspector\n17 Plains\n3 Guardians' Pledge\n2 Idyllic Grange\n3 Leonardo, Big Brother\n4 Battle Screech\n4 Lunarch Veteran\n4 Thraben Charm\n4 Kor Skyfisher\n4 Raffine's Informant\n3 Prismatic Strands\n2 Spider-Man, Web-Slinger\n4 Novice Inspector\n1 Eagles of the North\n1 Steadfast Unicorn\nsideboard\n1 Prismatic Strands\n2 Holy Light\n1 Palace Sentinels\n3 Dust to Dust\n4 Martyr of Sands\n2 Destroy Evil\n2 Journey to Nowhere\n"
}