{
  "schema_version": "1",
  "kind": "deck_text_blob",
  "generated_at": "2026-03-29T05:01:57Z",
  "format": "pauper",
  "source": "mtggoldfish",
  "deck_id": "7705891",
  "deck_name": "pauper-dimir-control-1e2279c1-d135-4609-8b99-83f2ab98c424",
  "deck_text": "4 Counterspell\n4 Lorien Revealed\n4 Sneaky Snacker\n4 Cast Down\n10 Island\n1 Swamp\n4 Contaminated Aquifer\n2 Bojuka Bog\n4 Snuff Out\n1 Foreboding Landscape\n1 Thorn of the Black Rose\n2 Gurmag Angler\n1 Gurmag Angler\n2 Thorn of the Black Rose\n4 Brainstorm\n1 Suffocating Fumes\n1 Preordain\n2 Spell Pierce\n4 Abandon Attachments\n1 Unexpected Fangs\n1 Murmuring Mystic\n1 Lose Focus\n1 Dispel\nsideboard\n1 Arms of Hadar\n2 Hydroblast\n3 Nihil Spellbomb\n2 Blue Elemental Blast\n4 Annul\n1 Blue Elemental Blast\n1 Hydroblast\n1 Blue Elemental Blast\n"
}