{
  "schema_version": "1",
  "kind": "deck_text_blob",
  "generated_at": "2026-03-29T17:24:19Z",
  "format": "pauper",
  "source": "mtggoldfish",
  "deck_id": "7706670",
  "deck_name": "pauper-mono-red-madness",
  "deck_text": "2 Firebrand Archer\n4 Highway Robbery\n3 Guttersnipe\n4 Sneaky Snacker\n4 Lava Dart\n3 Fireblast\n4 Grab the Prize\n18 Mountain\n4 Faithless Looting\n4 Lightning Bolt\n2 Stormshriek Feral\n4 Fiery Temper\n4 Thermo-Alchemist\nsideboard\n4 Kiln Fiend\n2 Red Elemental Blast\n4 Pyroblast\n3 Smash to Smithereens\n2 Tectonic Hazard\n"
}