{
  "schema_version": "1",
  "kind": "deck_text_blob",
  "generated_at": "2026-04-08T16:41:31Z",
  "format": "pauper",
  "source": "mtggoldfish",
  "deck_id": "7722463",
  "deck_name": "pauper-dimir-affinity",
  "deck_text": "4 Banishing Knack\n2 Black Mage's Rod\n3 Blood Fountain\n4 Cryogen Relic\n4 Fanatical Offering\n1 Island\n1 Metallic Rebuke\n4 Mistvault Bridge\n4 Myr Enforcer\n4 Refurbished Familiar\n4 Seat of the Synod\n2 Sewer-veillance Cam\n1 Silverbluff Bridge\n4 Steelfin Whale\n1 Swamp\n2 Tanglepool Bridge\n4 Thoughtcast\n3 Tooth of Chiss-Goria\n4 Utrom Monitor\n4 Vault of Whispers\nsideboard\n1 Blue Elemental Blast\n2 Dispel\n3 Duress\n4 Hydroblast\n2 Tithing Blade\n3 Tormod's Crypt\n"
}