{
  "schema_version": "1",
  "kind": "deck_text_blob",
  "generated_at": "2026-04-21T22:28:36Z",
  "format": "pauper",
  "source": "mtggoldfish",
  "deck_id": "7745986",
  "deck_name": "pauper-blue-terror-2b4f6710-ccb2-4660-b5f9-ea85c8875ec5",
  "deck_text": "1 Murmuring Mystic\n2 Contaminated Aquifer\n4 Snuff Out\n2 Contaminated Aquifer\n7 Snow-Covered Island\n2 Island\n2 Spell Pierce\n4 Brainstorm\n1 Ice Tunnel\n2 Island\n4 Lorien Revealed\n1 Suffocating Fumes\n4 Sneaky Snacker\n1 Consider\n3 Abandon Attachments\n4 Counterspell\n2 Tolarian Terror\n2 Unexpected Fangs\n4 Thought Scour\n2 Tolarian Terror\n1 Cast Down\n3 Mental Note\n2 Gurmag Angler\nsideboard\n2 Nihil Spellbomb\n1 Arms of Hadar\n1 Extract a Confession\n1 Envelop\n2 Annul\n1 Murmuring Mystic\n2 Hydroblast\n1 Blue Elemental Blast\n2 Steel Sabotage\n2 Hydroblast\n"
}