{
  "schema_version": "1",
  "kind": "deck_text_blob",
  "generated_at": "2026-04-21T14:52:54Z",
  "format": "pauper",
  "source": "mtggoldfish",
  "deck_id": "7745206",
  "deck_name": "pauper-mono-red-madness",
  "deck_text": "3 Fireblast\n3 Guttersnipe\n4 Highway Robbery\n4 Kessig Flamebreather\n4 Voldaren Epicure\n1 Fiery Temper\n4 Sneaky Snacker\n4 Grab the Prize\n3 Fiery Temper\n4 Faithless Looting\n4 Lightning Bolt\n4 Lava Dart\n2 Mountain\n2 Mountain\n2 Mountain\n2 Mountain\n2 Mountain\n2 Mountain\n2 Mountain\n2 Mountain\n2 Mountain\nsideboard\n2 Pyroblast\n2 Searing Blaze\n2 End the Festivities\n1 Relic of Progenitus\n3 Smash to Smithereens\n1 Flaring Pain\n1 Relic of Progenitus\n1 Relic of Progenitus\n2 Red Elemental Blast\n"
}