{
  "schema_version": "1",
  "kind": "archetype_radar",
  "generated_at": "2026-03-28T12:26:57Z",
  "format": "vintage",
  "source": "published-deck-texts",
  "archetype": {
    "name": "Oath of Druids",
    "href": "vintage-oath-of-druids"
  },
  "total_decks_analyzed": 12,
  "decks_failed": 0,
  "mainboard_cards": [
    {
      "card_name": "Force of Will",
      "appearances": 12,
      "total_copies": 48,
      "max_copies": 4,
      "avg_copies": 4.0,
      "inclusion_rate": 100.0,
      "expected_copies": 4.0,
      "copy_distribution": {
        "4": 12
      }
    },
    {
      "card_name": "Oath of Druids",
      "appearances": 12,
      "total_copies": 48,
      "max_copies": 4,
      "avg_copies": 4.0,
      "inclusion_rate": 100.0,
      "expected_copies": 4.0,
      "copy_distribution": {
        "4": 12
      }
    },
    {
      "card_name": "Forbidden Orchard",
      "appearances": 12,
      "total_copies": 48,
      "max_copies": 4,
      "avg_copies": 4.0,
      "inclusion_rate": 100.0,
      "expected_copies": 4.0,
      "copy_distribution": {
        "4": 12
      }
    },
    {
      "card_name": "Show and Tell",
      "appearances": 12,
      "total_copies": 45,
      "max_copies": 4,
      "avg_copies": 3.75,
      "inclusion_rate": 100.0,
      "expected_copies": 3.75,
      "copy_distribution": {
        "4": 9,
        "3": 3
      }
    },
    {
      "card_name": "Atraxa, Grand Unifier",
      "appearances": 12,
      "total_copies": 44,
      "max_copies": 4,
      "avg_copies": 3.67,
      "inclusion_rate": 100.0,
      "expected_copies": 3.67,
      "copy_distribution": {
        "4": 8,
        "3": 4
      }
    },
    {
      "card_name": "Tropical Island",
      "appearances": 12,
      "total_copies": 36,
      "max_copies": 3,
      "avg_copies": 3.0,
      "inclusion_rate": 100.0,
      "expected_copies": 3.0,
      "copy_distribution": {
        "3": 12
      }
    },
    {
      "card_name": "Ponder",
      "appearances": 11,
      "total_copies": 35,
      "max_copies": 4,
      "avg_copies": 3.18,
      "inclusion_rate": 91.7,
      "expected_copies": 2.92,
      "copy_distribution": {
        "4": 4,
        "3": 6,
        "1": 1,
        "0": 1
      }
    },
    {
      "card_name": "Flusterstorm",
      "appearances": 12,
      "total_copies": 26,
      "max_copies": 3,
      "avg_copies": 2.17,
      "inclusion_rate": 100.0,
      "expected_copies": 2.17,
      "copy_distribution": {
        "3": 2,
        "2": 10
      }
    },
    {
      "card_name": "Underground Sea",
      "appearances": 12,
      "total_copies": 24,
      "max_copies": 2,
      "avg_copies": 2.0,
      "inclusion_rate": 100.0,
      "expected_copies": 2.0,
      "copy_distribution": {
        "2": 12
      }
    },
    {
      "card_name": "Boseiju, Who Endures",
      "appearances": 12,
      "total_copies": 24,
      "max_copies": 2,
      "avg_copies": 2.0,
      "inclusion_rate": 100.0,
      "expected_copies": 2.0,
      "copy_distribution": {
        "2": 12
      }
    },
    {
      "card_name": "Oko, Thief of Crowns",
      "appearances": 12,
      "total_copies": 22,
      "max_copies": 2,
      "avg_copies": 1.83,
      "inclusion_rate": 100.0,
      "expected_copies": 1.83,
      "copy_distribution": {
        "2": 10,
        "1": 2
      }
    },
    {
      "card_name": "Polluted Delta",
      "appearances": 12,
      "total_copies": 20,
      "max_copies": 4,
      "avg_copies": 1.67,
      "inclusion_rate": 100.0,
      "expected_copies": 1.67,
      "copy_distribution": {
        "4": 1,
        "2": 5,
        "1": 6
      }
    },
    {
      "card_name": "Stock Up",
      "appearances": 8,
      "total_copies": 17,
      "max_copies": 3,
      "avg_copies": 2.12,
      "inclusion_rate": 66.7,
      "expected_copies": 1.42,
      "copy_distribution": {
        "3": 1,
        "2": 7,
        "0": 4
      }
    },
    {
      "card_name": "Scalding Tarn",
      "appearances": 11,
      "total_copies": 16,
      "max_copies": 2,
      "avg_copies": 1.45,
      "inclusion_rate": 91.7,
      "expected_copies": 1.33,
      "copy_distribution": {
        "2": 5,
        "1": 6,
        "0": 1
      }
    },
    {
      "card_name": "Force of Negation",
      "appearances": 12,
      "total_copies": 14,
      "max_copies": 2,
      "avg_copies": 1.17,
      "inclusion_rate": 100.0,
      "expected_copies": 1.17,
      "copy_distribution": {
        "2": 2,
        "1": 10
      }
    },
    {
      "card_name": "Null Rod",
      "appearances": 11,
      "total_copies": 14,
      "max_copies": 2,
      "avg_copies": 1.27,
      "inclusion_rate": 91.7,
      "expected_copies": 1.17,
      "copy_distribution": {
        "2": 3,
        "1": 8,
        "0": 1
      }
    },
    {
      "card_name": "Ancestral Recall",
      "appearances": 12,
      "total_copies": 12,
      "max_copies": 1,
      "avg_copies": 1.0,
      "inclusion_rate": 100.0,
      "expected_copies": 1.0,
      "copy_distribution": {
        "1": 12
      }
    },
    {
      "card_name": "Time Walk",
      "appearances": 12,
      "total_copies": 12,
      "max_copies": 1,
      "avg_copies": 1.0,
      "inclusion_rate": 100.0,
      "expected_copies": 1.0,
      "copy_distribution": {
        "1": 12
      }
    },
    {
      "card_name": "Mox Jet",
      "appearances": 12,
      "total_copies": 12,
      "max_copies": 1,
      "avg_copies": 1.0,
      "inclusion_rate": 100.0,
      "expected_copies": 1.0,
      "copy_distribution": {
        "1": 12
      }
    },
    {
      "card_name": "Mox Emerald",
      "appearances": 12,
      "total_copies": 12,
      "max_copies": 1,
      "avg_copies": 1.0,
      "inclusion_rate": 100.0,
      "expected_copies": 1.0,
      "copy_distribution": {
        "1": 12
      }
    },
    {
      "card_name": "Mox Pearl",
      "appearances": 12,
      "total_copies": 12,
      "max_copies": 1,
      "avg_copies": 1.0,
      "inclusion_rate": 100.0,
      "expected_copies": 1.0,
      "copy_distribution": {
        "1": 12
      }
    },
    {
      "card_name": "Mox Sapphire",
      "appearances": 12,
      "total_copies": 12,
      "max_copies": 1,
      "avg_copies": 1.0,
      "inclusion_rate": 100.0,
      "expected_copies": 1.0,
      "copy_distribution": {
        "1": 12
      }
    },
    {
      "card_name": "Demonic Tutor",
      "appearances": 12,
      "total_copies": 12,
      "max_copies": 1,
      "avg_copies": 1.0,
      "inclusion_rate": 100.0,
      "expected_copies": 1.0,
      "copy_distribution": {
        "1": 12
      }
    },
    {
      "card_name": "Black Lotus",
      "appearances": 12,
      "total_copies": 12,
      "max_copies": 1,
      "avg_copies": 1.0,
      "inclusion_rate": 100.0,
      "expected_copies": 1.0,
      "copy_distribution": {
        "1": 12
      }
    },
    {
      "card_name": "Brainstorm",
      "appearances": 12,
      "total_copies": 12,
      "max_copies": 1,
      "avg_copies": 1.0,
      "inclusion_rate": 100.0,
      "expected_copies": 1.0,
      "copy_distribution": {
        "1": 12
      }
    },
    {
      "card_name": "Strip Mine",
      "appearances": 12,
      "total_copies": 12,
      "max_copies": 1,
      "avg_copies": 1.0,
      "inclusion_rate": 100.0,
      "expected_copies": 1.0,
      "copy_distribution": {
        "1": 12
      }
    },
    {
      "card_name": "Vexing Bauble",
      "appearances": 12,
      "total_copies": 12,
      "max_copies": 1,
      "avg_copies": 1.0,
      "inclusion_rate": 100.0,
      "expected_copies": 1.0,
      "copy_distribution": {
        "1": 12
      }
    },
    {
      "card_name": "Gaea's Blessing",
      "appearances": 12,
      "total_copies": 12,
      "max_copies": 1,
      "avg_copies": 1.0,
      "inclusion_rate": 100.0,
      "expected_copies": 1.0,
      "copy_distribution": {
        "1": 12
      }
    },
    {
      "card_name": "Vampiric Tutor",
      "appearances": 11,
      "total_copies": 11,
      "max_copies": 1,
      "avg_copies": 1.0,
      "inclusion_rate": 91.7,
      "expected_copies": 0.92,
      "copy_distribution": {
        "1": 11,
        "0": 1
      }
    },
    {
      "card_name": "Gitaxian Probe",
      "appearances": 11,
      "total_copies": 11,
      "max_copies": 1,
      "avg_copies": 1.0,
      "inclusion_rate": 91.7,
      "expected_copies": 0.92,
      "copy_distribution": {
        "1": 11,
        "0": 1
      }
    },
    {
      "card_name": "Mental Misstep",
      "appearances": 11,
      "total_copies": 11,
      "max_copies": 1,
      "avg_copies": 1.0,
      "inclusion_rate": 91.7,
      "expected_copies": 0.92,
      "copy_distribution": {
        "1": 11,
        "0": 1
      }
    },
    {
      "card_name": "Hedge Maze",
      "appearances": 11,
      "total_copies": 11,
      "max_copies": 1,
      "avg_copies": 1.0,
      "inclusion_rate": 91.7,
      "expected_copies": 0.92,
      "copy_distribution": {
        "1": 11,
        "0": 1
      }
    },
    {
      "card_name": "Misty Rainforest",
      "appearances": 11,
      "total_copies": 11,
      "max_copies": 1,
      "avg_copies": 1.0,
      "inclusion_rate": 91.7,
      "expected_copies": 0.92,
      "copy_distribution": {
        "1": 11,
        "0": 1
      }
    },
    {
      "card_name": "Flash",
      "appearances": 9,
      "total_copies": 9,
      "max_copies": 1,
      "avg_copies": 1.0,
      "inclusion_rate": 75.0,
      "expected_copies": 0.75,
      "copy_distribution": {
        "1": 9,
        "0": 3
      }
    },
    {
      "card_name": "Thoughtseize",
      "appearances": 4,
      "total_copies": 9,
      "max_copies": 3,
      "avg_copies": 2.25,
      "inclusion_rate": 33.3,
      "expected_copies": 0.75,
      "copy_distribution": {
        "3": 1,
        "2": 3,
        "0": 8
      }
    },
    {
      "card_name": "Flooded Strand",
      "appearances": 6,
      "total_copies": 6,
      "max_copies": 1,
      "avg_copies": 1.0,
      "inclusion_rate": 50.0,
      "expected_copies": 0.5,
      "copy_distribution": {
        "1": 6,
        "0": 6
      }
    },
    {
      "card_name": "Island",
      "appearances": 5,
      "total_copies": 5,
      "max_copies": 1,
      "avg_copies": 1.0,
      "inclusion_rate": 41.7,
      "expected_copies": 0.42,
      "copy_distribution": {
        "1": 5,
        "0": 7
      }
    },
    {
      "card_name": "Raph & Mikey, Troublemakers",
      "appearances": 4,
      "total_copies": 4,
      "max_copies": 1,
      "avg_copies": 1.0,
      "inclusion_rate": 33.3,
      "expected_copies": 0.33,
      "copy_distribution": {
        "1": 4,
        "0": 8
      }
    },
    {
      "card_name": "Mana Crypt",
      "appearances": 2,
      "total_copies": 2,
      "max_copies": 1,
      "avg_copies": 1.0,
      "inclusion_rate": 16.7,
      "expected_copies": 0.17,
      "copy_distribution": {
        "1": 2,
        "0": 10
      }
    },
    {
      "card_name": "Snow-Covered Island",
      "appearances": 2,
      "total_copies": 2,
      "max_copies": 1,
      "avg_copies": 1.0,
      "inclusion_rate": 16.7,
      "expected_copies": 0.17,
      "copy_distribution": {
        "1": 2,
        "0": 10
      }
    },
    {
      "card_name": "Misdirection",
      "appearances": 1,
      "total_copies": 1,
      "max_copies": 1,
      "avg_copies": 1.0,
      "inclusion_rate": 8.3,
      "expected_copies": 0.08,
      "copy_distribution": {
        "1": 1,
        "0": 11
      }
    },
    {
      "card_name": "Mox Ruby",
      "appearances": 1,
      "total_copies": 1,
      "max_copies": 1,
      "avg_copies": 1.0,
      "inclusion_rate": 8.3,
      "expected_copies": 0.08,
      "copy_distribution": {
        "1": 1,
        "0": 11
      }
    },
    {
      "card_name": "Narset, Parter of Veils",
      "appearances": 1,
      "total_copies": 1,
      "max_copies": 1,
      "avg_copies": 1.0,
      "inclusion_rate": 8.3,
      "expected_copies": 0.08,
      "copy_distribution": {
        "1": 1,
        "0": 11
      }
    }
  ],
  "sideboard_cards": [
    {
      "card_name": "Abrupt Decay",
      "appearances": 12,
      "total_copies": 34,
      "max_copies": 3,
      "avg_copies": 2.83,
      "inclusion_rate": 100.0,
      "expected_copies": 2.83,
      "copy_distribution": {
        "3": 10,
        "2": 2
      }
    },
    {
      "card_name": "Null Rod",
      "appearances": 12,
      "total_copies": 29,
      "max_copies": 3,
      "avg_copies": 2.42,
      "inclusion_rate": 100.0,
      "expected_copies": 2.42,
      "copy_distribution": {
        "3": 8,
        "2": 1,
        "1": 3
      }
    },
    {
      "card_name": "Tormod's Crypt",
      "appearances": 5,
      "total_copies": 20,
      "max_copies": 4,
      "avg_copies": 4.0,
      "inclusion_rate": 41.7,
      "expected_copies": 1.67,
      "copy_distribution": {
        "4": 5,
        "0": 7
      }
    },
    {
      "card_name": "Unable to Scream",
      "appearances": 5,
      "total_copies": 15,
      "max_copies": 3,
      "avg_copies": 3.0,
      "inclusion_rate": 41.7,
      "expected_copies": 1.25,
      "copy_distribution": {
        "3": 5,
        "0": 7
      }
    },
    {
      "card_name": "Leyline of the Void",
      "appearances": 4,
      "total_copies": 15,
      "max_copies": 4,
      "avg_copies": 3.75,
      "inclusion_rate": 33.3,
      "expected_copies": 1.25,
      "copy_distribution": {
        "4": 3,
        "3": 1,
        "0": 8
      }
    },
    {
      "card_name": "Ravenous Trap",
      "appearances": 3,
      "total_copies": 12,
      "max_copies": 4,
      "avg_copies": 4.0,
      "inclusion_rate": 25.0,
      "expected_copies": 1.0,
      "copy_distribution": {
        "4": 3,
        "0": 9
      }
    },
    {
      "card_name": "Force of Negation",
      "appearances": 11,
      "total_copies": 11,
      "max_copies": 1,
      "avg_copies": 1.0,
      "inclusion_rate": 91.7,
      "expected_copies": 0.92,
      "copy_distribution": {
        "1": 11,
        "0": 1
      }
    },
    {
      "card_name": "The Tabernacle at Pendrell Vale",
      "appearances": 10,
      "total_copies": 10,
      "max_copies": 1,
      "avg_copies": 1.0,
      "inclusion_rate": 83.3,
      "expected_copies": 0.83,
      "copy_distribution": {
        "1": 10,
        "0": 2
      }
    },
    {
      "card_name": "Consign to Memory",
      "appearances": 5,
      "total_copies": 7,
      "max_copies": 2,
      "avg_copies": 1.4,
      "inclusion_rate": 41.7,
      "expected_copies": 0.58,
      "copy_distribution": {
        "2": 2,
        "1": 3,
        "0": 7
      }
    },
    {
      "card_name": "Void Mirror",
      "appearances": 2,
      "total_copies": 6,
      "max_copies": 3,
      "avg_copies": 3.0,
      "inclusion_rate": 16.7,
      "expected_copies": 0.5,
      "copy_distribution": {
        "3": 2,
        "0": 10
      }
    },
    {
      "card_name": "Dismember",
      "appearances": 5,
      "total_copies": 5,
      "max_copies": 1,
      "avg_copies": 1.0,
      "inclusion_rate": 41.7,
      "expected_copies": 0.42,
      "copy_distribution": {
        "1": 5,
        "0": 7
      }
    },
    {
      "card_name": "Thoughtseize",
      "appearances": 4,
      "total_copies": 4,
      "max_copies": 1,
      "avg_copies": 1.0,
      "inclusion_rate": 33.3,
      "expected_copies": 0.33,
      "copy_distribution": {
        "1": 4,
        "0": 8
      }
    },
    {
      "card_name": "Long Goodbye",
      "appearances": 2,
      "total_copies": 3,
      "max_copies": 2,
      "avg_copies": 1.5,
      "inclusion_rate": 16.7,
      "expected_copies": 0.25,
      "copy_distribution": {
        "2": 1,
        "1": 1,
        "0": 10
      }
    },
    {
      "card_name": "Serra's Emissary",
      "appearances": 2,
      "total_copies": 2,
      "max_copies": 1,
      "avg_copies": 1.0,
      "inclusion_rate": 16.7,
      "expected_copies": 0.17,
      "copy_distribution": {
        "1": 2,
        "0": 10
      }
    },
    {
      "card_name": "Unmoored Ego",
      "appearances": 2,
      "total_copies": 2,
      "max_copies": 1,
      "avg_copies": 1.0,
      "inclusion_rate": 16.7,
      "expected_copies": 0.17,
      "copy_distribution": {
        "1": 2,
        "0": 10
      }
    },
    {
      "card_name": "Soul-Guide Lantern",
      "appearances": 1,
      "total_copies": 1,
      "max_copies": 1,
      "avg_copies": 1.0,
      "inclusion_rate": 8.3,
      "expected_copies": 0.08,
      "copy_distribution": {
        "1": 1,
        "0": 11
      }
    },
    {
      "card_name": "Veil of Summer",
      "appearances": 1,
      "total_copies": 1,
      "max_copies": 1,
      "avg_copies": 1.0,
      "inclusion_rate": 8.3,
      "expected_copies": 0.08,
      "copy_distribution": {
        "1": 1,
        "0": 11
      }
    },
    {
      "card_name": "Force of Vigor",
      "appearances": 1,
      "total_copies": 1,
      "max_copies": 1,
      "avg_copies": 1.0,
      "inclusion_rate": 8.3,
      "expected_copies": 0.08,
      "copy_distribution": {
        "1": 1,
        "0": 11
      }
    },
    {
      "card_name": "Mindbreak Trap",
      "appearances": 1,
      "total_copies": 1,
      "max_copies": 1,
      "avg_copies": 1.0,
      "inclusion_rate": 8.3,
      "expected_copies": 0.08,
      "copy_distribution": {
        "1": 1,
        "0": 11
      }
    },
    {
      "card_name": "Oko, Thief of Crowns",
      "appearances": 1,
      "total_copies": 1,
      "max_copies": 1,
      "avg_copies": 1.0,
      "inclusion_rate": 8.3,
      "expected_copies": 0.08,
      "copy_distribution": {
        "1": 1,
        "0": 11
      }
    }
  ]
}