{
  "schema_version": "1",
  "kind": "archetype_decks",
  "generated_at": "2026-03-30T10:42:13Z",
  "format": "modern",
  "source": "both",
  "archetype": {
    "name": "Grixis Reanimator",
    "href": "modern-grixis-reanimator"
  },
  "decks": [
    {
      "date": "2026-03-30",
      "number": "7707792",
      "player": "jk1592",
      "event": "Modern Challenge 32 2026-03-30 (1)",
      "result": "24th",
      "name": "modern-grixis-reanimator",
      "source": "mtggoldfish",
      "deck_text_path": "archive/deck-texts/modern/7707792.json"
    },
    {
      "date": "2026-03-30",
      "number": "7707732",
      "player": "jk1592",
      "event": "Modern Challenge 32 2026-03-30",
      "result": "24th",
      "name": "modern-grixis-reanimator",
      "source": "mtggoldfish",
      "deck_text_path": "archive/deck-texts/modern/7707732.json"
    },
    {
      "date": "2026-03-30",
      "number": "7707433",
      "player": "dndias",
      "event": "Modern League 2026-03-30",
      "result": "5-0",
      "name": "modern-grixis-reanimator",
      "source": "mtggoldfish",
      "deck_text_path": "archive/deck-texts/modern/7707433.json"
    },
    {
      "date": "2026-03-29",
      "number": "7706819",
      "player": "hunnhu",
      "event": "Modern Challenge 32 2026-03-29 (1)",
      "result": "31st",
      "name": "modern-grixis-reanimator",
      "source": "mtggoldfish",
      "deck_text_path": "archive/deck-texts/modern/7706819.json"
    },
    {
      "date": "2026-03-29",
      "number": "7706530",
      "player": "IgorAS",
      "event": "Vespa TCG - 3 Etapa LMG 28/03",
      "result": "8th",
      "name": "modern-grixis-reanimator",
      "source": "mtggoldfish",
      "deck_text_path": "archive/deck-texts/modern/7706530.json"
    },
    {
      "date": "2026-03-28",
      "number": "7706713",
      "player": "Gustavo Ohana",
      "event": "3 Torneio Super Modern",
      "result": "2nd",
      "name": "modern-grixis-reanimator",
      "source": "mtggoldfish",
      "deck_text_path": "archive/deck-texts/modern/7706713.json"
    },
    {
      "date": "2026-03-28",
      "number": "7705628",
      "player": "Ma7x",
      "event": "Modern Challenge 64 2026-03-28",
      "result": "28th",
      "name": "modern-grixis-reanimator",
      "source": "mtggoldfish",
      "deck_text_path": "archive/deck-texts/modern/7705628.json"
    },
    {
      "date": "2026-03-28",
      "number": "7705524",
      "player": "__Magic__Dan__",
      "event": "Modern Showcase Qualifier 2026-03-28",
      "result": "3rd",
      "name": "modern-grixis-reanimator",
      "source": "mtggoldfish",
      "deck_text_path": "archive/deck-texts/modern/7705524.json"
    },
    {
      "date": "2026-03-28",
      "number": "7705473",
      "player": "DB_Mateusf34",
      "event": "Modern League 2026-03-28",
      "result": "5-0",
      "name": "modern-grixis-reanimator",
      "source": "mtggoldfish",
      "deck_text_path": "archive/deck-texts/modern/7705473.json"
    },
    {
      "date": "2026-03-28",
      "number": "7704415",
      "player": "Skelley",
      "event": "Modern League 2026-03-28",
      "result": "5-0",
      "name": "modern-grixis-reanimator",
      "source": "mtggoldfish",
      "deck_text_path": "archive/deck-texts/modern/7704415.json"
    },
    {
      "date": "2026-03-26",
      "number": "7703023",
      "player": "Wiltron92",
      "event": "Modern League 2026-03-26",
      "result": "5-0",
      "name": "modern-grixis-reanimator",
      "source": "mtggoldfish",
      "deck_text_path": "archive/deck-texts/modern/7703023.json"
    },
    {
      "date": "2026-03-26",
      "number": "7702780",
      "player": "Wiltron92",
      "event": "Modern Challenge 64 2026-03-26",
      "result": "14th",
      "name": "modern-grixis-reanimator",
      "source": "mtggoldfish",
      "deck_text_path": "archive/deck-texts/modern/7702780.json"
    },
    {
      "date": "2026-03-24",
      "number": "7699742",
      "player": "GLSwadow",
      "event": "Modern Challenge 64 2026-03-24",
      "result": "16th",
      "name": "modern-grixis-reanimator",
      "source": "mtggoldfish",
      "deck_text_path": "archive/deck-texts/modern/7699742.json"
    }
  ]
}