{
  "schema_version": "1",
  "kind": "archetype_decks",
  "generated_at": "2026-03-30T07:52:19Z",
  "format": "standard",
  "source": "both",
  "archetype": {
    "name": "Boros Dragons",
    "href": "standard-boros-dragons-woe"
  },
  "decks": [
    {
      "date": "2026-03-25",
      "number": "7700558",
      "player": "Ellmorganacg",
      "event": "$$Big Brain Games #8 $$",
      "result": "10th",
      "name": "standard-boros-dragons-woe",
      "source": "mtggoldfish",
      "deck_text_path": "archive/deck-texts/standard/7700558.json"
    }
  ]
}