{
  "schema_version": "1",
  "kind": "archetype_decks",
  "generated_at": "2026-04-26T12:32:29Z",
  "format": "standard",
  "source": "both",
  "archetype": {
    "name": "Dimir Midrange",
    "href": "standard-dimir-midrange-woe"
  },
  "decks": [
    {
      "date": "2026-04-23",
      "number": "7747585",
      "player": "gazmon48",
      "event": "Standard Challenge 32 2026-04-23",
      "result": "29th",
      "name": "standard-dimir-midrange-woe",
      "source": "mtggoldfish",
      "deck_text_path": "archive/deck-texts/standard/7747585.json"
    },
    {
      "date": "2026-04-23",
      "number": "7747580",
      "player": "Arianne",
      "event": "Standard Challenge 32 2026-04-23",
      "result": "25th",
      "name": "standard-dimir-midrange-woe",
      "source": "mtggoldfish",
      "deck_text_path": "archive/deck-texts/standard/7747580.json"
    },
    {
      "date": "2026-04-21",
      "number": "7747846",
      "player": "Kako_Ferrer",
      "event": "Standard Challenge 32 2026-04-21 (1)",
      "result": "17th",
      "name": "standard-dimir-midrange-woe",
      "source": "mtggoldfish",
      "deck_text_path": "archive/deck-texts/standard/7747846.json"
    },
    {
      "date": "2026-04-21",
      "number": "7747825",
      "player": "_Falcon_",
      "event": "Standard Challenge 32 2026-04-21 (1)",
      "result": "29th",
      "name": "standard-dimir-midrange-woe",
      "source": "mtggoldfish",
      "deck_text_path": "archive/deck-texts/standard/7747825.json"
    },
    {
      "date": "2026-04-21",
      "number": "7747821",
      "player": "Arianne",
      "event": "Standard Challenge 32 2026-04-21 (1)",
      "result": "3rd",
      "name": "standard-dimir-midrange-woe",
      "source": "mtggoldfish",
      "deck_text_path": "archive/deck-texts/standard/7747821.json"
    },
    {
      "date": "2026-04-21",
      "number": "7746186",
      "player": "Kako_Ferrer",
      "event": "Standard Challenge 32 2026-04-21",
      "result": "17th",
      "name": "standard-dimir-midrange-woe",
      "source": "mtggoldfish",
      "deck_text_path": "archive/deck-texts/standard/7746186.json"
    },
    {
      "date": "2026-04-21",
      "number": "7746165",
      "player": "_Falcon_",
      "event": "Standard Challenge 32 2026-04-21",
      "result": "29th",
      "name": "standard-dimir-midrange-woe",
      "source": "mtggoldfish",
      "deck_text_path": "archive/deck-texts/standard/7746165.json"
    },
    {
      "date": "2026-04-21",
      "number": "7746161",
      "player": "Arianne",
      "event": "Standard Challenge 32 2026-04-21",
      "result": "3rd",
      "name": "standard-dimir-midrange-woe",
      "source": "mtggoldfish",
      "deck_text_path": "archive/deck-texts/standard/7746161.json"
    },
    {
      "date": "2026-04-20",
      "number": "7744055",
      "player": "Kako_Ferrer",
      "event": "Standard Challenge 32 2026-04-20",
      "result": "2nd",
      "name": "standard-dimir-midrange-woe",
      "source": "mtggoldfish",
      "deck_text_path": "archive/deck-texts/standard/7744055.json"
    }
  ]
}