{
  "schema_version": "1",
  "kind": "deck_text_blob",
  "generated_at": "2026-03-24T12:46:21Z",
  "format": "modern",
  "source": "mtggoldfish",
  "deck_id": "7694054",
  "deck_name": "modern-ruby-storm",
  "deck_text": "4 Pyretic Ritual\n2 Bloodstained Mire\n4 Mountain\n4 Reckless Impulse\n4 Wrenn's Resolve\n3 Past in Flames\n1 Elegant Parlor\n1 Sacred Foundry\n4 Desperate Ritual\n2 Artist's Talent\n1 Gemstone Caverns\n1 Sunbaked Canyon\n2 Strike It Rich\n2 Valakut Awakening\n4 Ruby Medallion\n2 Wish\n4 Ral, Monsoon Mage\n1 Grapeshot\n1 Thundering Falls\n2 Scalding Tarn\n2 Arid Mesa\n3 Wooded Foothills\n2 Glimpse the Impossible\n4 Manamorphose\nsideboard\n4 Prismatic Ending\n4 Orim's Chant\n1 Past in Flames\n1 Grapeshot\n2 Fire Magic\n1 Empty the Warrens\n2 Untimely Malfunction\n"
}