{
  "schema_version": "1",
  "kind": "deck_text_blob",
  "generated_at": "2026-04-04T00:53:41Z",
  "format": "modern",
  "source": "mtggoldfish",
  "deck_id": "7713961",
  "deck_name": "modern-yawgmoth-9bd3dc9a-1da1-442e-9b88-6ef2a027e80b",
  "deck_text": "4 Badgermole Cub\n4 Delighted Halfling\n4 Yawgmoth, Thran Physician\n3 Walking Ballista\n1 Swamp\n2 Underground Mortuary\n1 Endurance\n1 Formidable Speaker\n1 Strangleroot Geist\n1 Virulent Emissary\n2 Overgrown Tomb\n1 Forest\n1 Forest\n3 Malevolent Rumble\n2 Dredger's Insight\n1 Grist, the Hunger Tide\n2 Boseiju, Who Endures\n3 Misty Rainforest\n4 Verdant Catacombs\n3 Spymaster's Vault\n1 Dryad Arbor\n3 Green Sun's Zenith\n2 Chord of Calling\n4 Agatha's Soul Cauldron\n2 Orcish Bowmasters\n3 Young Wolf\n1 Wooded Foothills\nsideboard\n1 Endurance\n3 Fatal Push\n1 Fulminator Mage\n1 Ashiok, Dream Render\n1 Culling Ritual\n1 Damping Sphere\n1 Force of Vigor\n2 Thoughtseize\n1 Kraul Harpooner\n1 Outland Liberator\n1 Soulless Jailer\n1 Vexing Bauble\n"
}