{
  "schema_version": "1",
  "kind": "publisher_run",
  "generated_at": "2026-03-28T08:25:25Z",
  "command": "scrape-deck-texts-pauper",
  "status": "success",
  "max_stale_hours": 24,
  "summary": {
    "success": 46,
    "skipped": 334
  },
  "results": [
    {
      "scope": "archetype-list",
      "status": "success",
      "format": "pauper",
      "path": "latest/archetypes/pauper.json"
    },
    {
      "scope": "archetype-decks",
      "status": "skipped",
      "format": "pauper",
      "archetype": "4c-ephemerate",
      "path": "latest/decks/pauper/4c-ephemerate.json",
      "message": "No decks found within the last 7 days."
    },
    {
      "scope": "archetype-decks",
      "status": "skipped",
      "format": "pauper",
      "archetype": "azorius-faeries",
      "path": "latest/decks/pauper/azorius-faeries.json",
      "message": "No decks found within the last 7 days."
    },
    {
      "scope": "archetype-decks",
      "status": "skipped",
      "format": "pauper",
      "archetype": "black-burn",
      "path": "latest/decks/pauper/black-burn.json",
      "message": "No decks found within the last 7 days."
    },
    {
      "scope": "archetype-decks",
      "status": "success",
      "format": "pauper",
      "archetype": "black-sacrifice",
      "path": "latest/decks/pauper/black-sacrifice.json"
    },
    {
      "scope": "archetype-decks",
      "status": "success",
      "format": "pauper",
      "archetype": "blue-terror",
      "path": "latest/decks/pauper/blue-terror.json"
    },
    {
      "scope": "archetype-decks",
      "status": "success",
      "format": "pauper",
      "archetype": "bogles",
      "path": "latest/decks/pauper/bogles.json"
    },
    {
      "scope": "archetype-decks",
      "status": "success",
      "format": "pauper",
      "archetype": "boros-bully",
      "path": "latest/decks/pauper/boros-bully.json"
    },
    {
      "scope": "archetype-decks",
      "status": "success",
      "format": "pauper",
      "archetype": "boros-moxite",
      "path": "latest/decks/pauper/boros-moxite.json"
    },
    {
      "scope": "archetype-decks",
      "status": "success",
      "format": "pauper",
      "archetype": "boros-synthesizer",
      "path": "latest/decks/pauper/boros-synthesizer.json"
    },
    {
      "scope": "archetype-decks",
      "status": "success",
      "format": "pauper",
      "archetype": "burn",
      "path": "latest/decks/pauper/burn.json"
    },
    {
      "scope": "archetype-decks",
      "status": "success",
      "format": "pauper",
      "archetype": "caw-gates",
      "path": "latest/decks/pauper/caw-gates.json"
    },
    {
      "scope": "archetype-decks",
      "status": "skipped",
      "format": "pauper",
      "archetype": "cycle-storm",
      "path": "latest/decks/pauper/cycle-storm.json",
      "message": "No decks found within the last 7 days."
    },
    {
      "scope": "archetype-decks",
      "status": "skipped",
      "format": "pauper",
      "archetype": "devotion",
      "path": "latest/decks/pauper/devotion.json",
      "message": "No decks found within the last 7 days."
    },
    {
      "scope": "archetype-decks",
      "status": "success",
      "format": "pauper",
      "archetype": "dimir-affinity",
      "path": "latest/decks/pauper/dimir-affinity.json"
    },
    {
      "scope": "archetype-decks",
      "status": "success",
      "format": "pauper",
      "archetype": "dimir-control",
      "path": "latest/decks/pauper/dimir-control.json"
    },
    {
      "scope": "archetype-decks",
      "status": "success",
      "format": "pauper",
      "archetype": "dimir-faeries",
      "path": "latest/decks/pauper/dimir-faeries.json"
    },
    {
      "scope": "archetype-decks",
      "status": "success",
      "format": "pauper",
      "archetype": "dimir-terror",
      "path": "latest/decks/pauper/dimir-terror.json"
    },
    {
      "scope": "archetype-decks",
      "status": "success",
      "format": "pauper",
      "archetype": "dredge",
      "path": "latest/decks/pauper/dredge.json"
    },
    {
      "scope": "archetype-decks",
      "status": "success",
      "format": "pauper",
      "archetype": "elves",
      "path": "latest/decks/pauper/elves.json"
    },
    {
      "scope": "archetype-decks",
      "status": "success",
      "format": "pauper",
      "archetype": "ephemerate-tron",
      "path": "latest/decks/pauper/ephemerate-tron.json"
    },
    {
      "scope": "archetype-decks",
      "status": "success",
      "format": "pauper",
      "archetype": "esper-affinity",
      "path": "latest/decks/pauper/esper-affinity.json"
    },
    {
      "scope": "archetype-decks",
      "status": "success",
      "format": "pauper",
      "archetype": "esper-ephemerate",
      "path": "latest/decks/pauper/esper-ephemerate.json"
    },
    {
      "scope": "archetype-decks",
      "status": "success",
      "format": "pauper",
      "archetype": "familiars",
      "path": "latest/decks/pauper/familiars.json"
    },
    {
      "scope": "archetype-decks",
      "status": "success",
      "format": "pauper",
      "archetype": "food-gardens",
      "path": "latest/decks/pauper/food-gardens.json"
    },
    {
      "scope": "archetype-decks",
      "status": "success",
      "format": "pauper",
      "archetype": "glintblade",
      "path": "latest/decks/pauper/glintblade.json"
    },
    {
      "scope": "archetype-decks",
      "status": "skipped",
      "format": "pauper",
      "archetype": "goblins",
      "path": "latest/decks/pauper/goblins.json",
      "message": "No decks found within the last 7 days."
    },
    {
      "scope": "archetype-decks",
      "status": "success",
      "format": "pauper",
      "archetype": "golgari-gardens",
      "path": "latest/decks/pauper/golgari-gardens.json"
    },
    {
      "scope": "archetype-decks",
      "status": "skipped",
      "format": "pauper",
      "archetype": "golgari-ponza",
      "path": "latest/decks/pauper/golgari-ponza.json",
      "message": "No decks found within the last 7 days."
    },
    {
      "scope": "archetype-decks",
      "status": "success",
      "format": "pauper",
      "archetype": "grixis-affinity",
      "path": "latest/decks/pauper/grixis-affinity.json"
    },
    {
      "scope": "archetype-decks",
      "status": "success",
      "format": "pauper",
      "archetype": "gruul-ponza",
      "path": "latest/decks/pauper/gruul-ponza.json"
    },
    {
      "scope": "archetype-decks",
      "status": "success",
      "format": "pauper",
      "archetype": "gruul-ramp",
      "path": "latest/decks/pauper/gruul-ramp.json"
    },
    {
      "scope": "archetype-decks",
      "status": "skipped",
      "format": "pauper",
      "archetype": "infect",
      "path": "latest/decks/pauper/infect.json",
      "message": "No decks found within the last 7 days."
    },
    {
      "scope": "archetype-decks",
      "status": "success",
      "format": "pauper",
      "archetype": "izzet-faeries",
      "path": "latest/decks/pauper/izzet-faeries.json"
    },
    {
      "scope": "archetype-decks",
      "status": "success",
      "format": "pauper",
      "archetype": "izzet-terror",
      "path": "latest/decks/pauper/izzet-terror.json"
    },
    {
      "scope": "archetype-decks",
      "status": "skipped",
      "format": "pauper",
      "archetype": "jeskai-affinity",
      "path": "latest/decks/pauper/jeskai-affinity.json",
      "message": "No decks found within the last 7 days."
    },
    {
      "scope": "archetype-decks",
      "status": "success",
      "format": "pauper",
      "archetype": "jeskai-ephemerate",
      "path": "latest/decks/pauper/jeskai-ephemerate.json"
    },
    {
      "scope": "archetype-decks",
      "status": "success",
      "format": "pauper",
      "archetype": "jeskai-synthesizer",
      "path": "latest/decks/pauper/jeskai-synthesizer.json"
    },
    {
      "scope": "archetype-decks",
      "status": "success",
      "format": "pauper",
      "archetype": "jund-gardens",
      "path": "latest/decks/pauper/jund-gardens.json"
    },
    {
      "scope": "archetype-decks",
      "status": "success",
      "format": "pauper",
      "archetype": "jund-wildfire",
      "path": "latest/decks/pauper/jund-wildfire.json"
    },
    {
      "scope": "archetype-decks",
      "status": "success",
      "format": "pauper",
      "archetype": "kiln-fiend",
      "path": "latest/decks/pauper/kiln-fiend.json"
    },
    {
      "scope": "archetype-decks",
      "status": "success",
      "format": "pauper",
      "archetype": "madness-burn",
      "path": "latest/decks/pauper/madness-burn.json"
    },
    {
      "scope": "archetype-decks",
      "status": "skipped",
      "format": "pauper",
      "archetype": "mardu-synthesizer",
      "path": "latest/decks/pauper/mardu-synthesizer.json",
      "message": "No decks found within the last 7 days."
    },
    {
      "scope": "archetype-decks",
      "status": "success",
      "format": "pauper",
      "archetype": "mono-red-madness",
      "path": "latest/decks/pauper/mono-red-madness.json"
    },
    {
      "scope": "archetype-decks",
      "status": "skipped",
      "format": "pauper",
      "archetype": "mono-red-pingers",
      "path": "latest/decks/pauper/mono-red-pingers.json",
      "message": "No decks found within the last 7 days."
    },
    {
      "scope": "archetype-decks",
      "status": "success",
      "format": "pauper",
      "archetype": "mono-red-rally",
      "path": "latest/decks/pauper/mono-red-rally.json"
    },
    {
      "scope": "archetype-decks",
      "status": "success",
      "format": "pauper",
      "archetype": "mono-blue-faeries",
      "path": "latest/decks/pauper/mono-blue-faeries.json"
    },
    {
      "scope": "archetype-decks",
      "status": "skipped",
      "format": "pauper",
      "archetype": "mono-white-heroic",
      "path": "latest/decks/pauper/mono-white-heroic.json",
      "message": "No decks found within the last 7 days."
    },
    {
      "scope": "archetype-decks",
      "status": "success",
      "format": "pauper",
      "archetype": "naya-ephemerate",
      "path": "latest/decks/pauper/naya-ephemerate.json"
    },
    {
      "scope": "archetype-decks",
      "status": "skipped",
      "format": "pauper",
      "archetype": "orzhov-ephemerate",
      "path": "latest/decks/pauper/orzhov-ephemerate.json",
      "message": "No decks found within the last 7 days."
    },
    {
      "scope": "archetype-decks",
      "status": "success",
      "format": "pauper",
      "archetype": "poison-storm",
      "path": "latest/decks/pauper/poison-storm.json"
    },
    {
      "scope": "archetype-decks",
      "status": "success",
      "format": "pauper",
      "archetype": "ruby-storm",
      "path": "latest/decks/pauper/ruby-storm.json"
    },
    {
      "scope": "archetype-decks",
      "status": "skipped",
      "format": "pauper",
      "archetype": "selesnya-ramp",
      "path": "latest/decks/pauper/selesnya-ramp.json",
      "message": "No decks found within the last 7 days."
    },
    {
      "scope": "archetype-decks",
      "status": "success",
      "format": "pauper",
      "archetype": "serpentine-curve",
      "path": "latest/decks/pauper/serpentine-curve.json"
    },
    {
      "scope": "archetype-decks",
      "status": "success",
      "format": "pauper",
      "archetype": "slivers",
      "path": "latest/decks/pauper/slivers.json"
    },
    {
      "scope": "archetype-decks",
      "status": "success",
      "format": "pauper",
      "archetype": "spy-combo",
      "path": "latest/decks/pauper/spy-combo.json"
    },
    {
      "scope": "archetype-decks",
      "status": "skipped",
      "format": "pauper",
      "archetype": "storm",
      "path": "latest/decks/pauper/storm.json",
      "message": "No decks found within the last 7 days."
    },
    {
      "scope": "archetype-decks",
      "status": "success",
      "format": "pauper",
      "archetype": "tron",
      "path": "latest/decks/pauper/tron.json"
    },
    {
      "scope": "archetype-decks",
      "status": "success",
      "format": "pauper",
      "archetype": "turbo-fog",
      "path": "latest/decks/pauper/turbo-fog.json"
    },
    {
      "scope": "archetype-decks",
      "status": "success",
      "format": "pauper",
      "archetype": "walls-combo",
      "path": "latest/decks/pauper/walls-combo.json"
    },
    {
      "scope": "archetype-decks",
      "status": "success",
      "format": "pauper",
      "archetype": "white-aggro",
      "path": "latest/decks/pauper/white-aggro.json"
    },
    {
      "scope": "deck-text",
      "status": "skipped",
      "format": "pauper",
      "deck_id": "7692935",
      "path": "archive/deck-texts/pauper/7692935.json",
      "message": "Reused existing published deck-text blob."
    },
    {
      "scope": "deck-text",
      "status": "skipped",
      "format": "pauper",
      "deck_id": "7693128",
      "path": "archive/deck-texts/pauper/7693128.json",
      "message": "Reused existing published deck-text blob."
    },
    {
      "scope": "deck-text",
      "status": "skipped",
      "format": "pauper",
      "deck_id": "7693203",
      "path": "archive/deck-texts/pauper/7693203.json",
      "message": "Reused existing published deck-text blob."
    },
    {
      "scope": "deck-text",
      "status": "skipped",
      "format": "pauper",
      "deck_id": "7693224",
      "path": "archive/deck-texts/pauper/7693224.json",
      "message": "Reused existing published deck-text blob."
    },
    {
      "scope": "deck-text",
      "status": "skipped",
      "format": "pauper",
      "deck_id": "7693253",
      "path": "archive/deck-texts/pauper/7693253.json",
      "message": "Reused existing published deck-text blob."
    },
    {
      "scope": "deck-text",
      "status": "skipped",
      "format": "pauper",
      "deck_id": "7693287",
      "path": "archive/deck-texts/pauper/7693287.json",
      "message": "Reused existing published deck-text blob."
    },
    {
      "scope": "deck-text",
      "status": "skipped",
      "format": "pauper",
      "deck_id": "7693438",
      "path": "archive/deck-texts/pauper/7693438.json",
      "message": "Reused existing published deck-text blob."
    },
    {
      "scope": "deck-text",
      "status": "skipped",
      "format": "pauper",
      "deck_id": "7693584",
      "path": "archive/deck-texts/pauper/7693584.json",
      "message": "Reused existing published deck-text blob."
    },
    {
      "scope": "deck-text",
      "status": "skipped",
      "format": "pauper",
      "deck_id": "7693935",
      "path": "archive/deck-texts/pauper/7693935.json",
      "message": "Reused existing published deck-text blob."
    },
    {
      "scope": "deck-text",
      "status": "skipped",
      "format": "pauper",
      "deck_id": "7694142",
      "path": "archive/deck-texts/pauper/7694142.json",
      "message": "Reused existing published deck-text blob."
    },
    {
      "scope": "deck-text",
      "status": "skipped",
      "format": "pauper",
      "deck_id": "7694590",
      "path": "archive/deck-texts/pauper/7694590.json",
      "message": "Reused existing published deck-text blob."
    },
    {
      "scope": "deck-text",
      "status": "skipped",
      "format": "pauper",
      "deck_id": "7694591",
      "path": "archive/deck-texts/pauper/7694591.json",
      "message": "Reused existing published deck-text blob."
    },
    {
      "scope": "deck-text",
      "status": "skipped",
      "format": "pauper",
      "deck_id": "7694592",
      "path": "archive/deck-texts/pauper/7694592.json",
      "message": "Reused existing published deck-text blob."
    },
    {
      "scope": "deck-text",
      "status": "skipped",
      "format": "pauper",
      "deck_id": "7694631",
      "path": "archive/deck-texts/pauper/7694631.json",
      "message": "Reused existing published deck-text blob."
    },
    {
      "scope": "deck-text",
      "status": "skipped",
      "format": "pauper",
      "deck_id": "7694811",
      "path": "archive/deck-texts/pauper/7694811.json",
      "message": "Reused existing published deck-text blob."
    },
    {
      "scope": "deck-text",
      "status": "skipped",
      "format": "pauper",
      "deck_id": "7694812",
      "path": "archive/deck-texts/pauper/7694812.json",
      "message": "Reused existing published deck-text blob."
    },
    {
      "scope": "deck-text",
      "status": "skipped",
      "format": "pauper",
      "deck_id": "7694931",
      "path": "archive/deck-texts/pauper/7694931.json",
      "message": "Reused existing published deck-text blob."
    },
    {
      "scope": "deck-text",
      "status": "skipped",
      "format": "pauper",
      "deck_id": "7694932",
      "path": "archive/deck-texts/pauper/7694932.json",
      "message": "Reused existing published deck-text blob."
    },
    {
      "scope": "deck-text",
      "status": "skipped",
      "format": "pauper",
      "deck_id": "7694933",
      "path": "archive/deck-texts/pauper/7694933.json",
      "message": "Reused existing published deck-text blob."
    },
    {
      "scope": "deck-text",
      "status": "skipped",
      "format": "pauper",
      "deck_id": "7694934",
      "path": "archive/deck-texts/pauper/7694934.json",
      "message": "Reused existing published deck-text blob."
    },
    {
      "scope": "deck-text",
      "status": "skipped",
      "format": "pauper",
      "deck_id": "7694935",
      "path": "archive/deck-texts/pauper/7694935.json",
      "message": "Reused existing published deck-text blob."
    },
    {
      "scope": "deck-text",
      "status": "skipped",
      "format": "pauper",
      "deck_id": "7694936",
      "path": "archive/deck-texts/pauper/7694936.json",
      "message": "Reused existing published deck-text blob."
    },
    {
      "scope": "deck-text",
      "status": "skipped",
      "format": "pauper",
      "deck_id": "7694937",
      "path": "archive/deck-texts/pauper/7694937.json",
      "message": "Reused existing published deck-text blob."
    },
    {
      "scope": "deck-text",
      "status": "skipped",
      "format": "pauper",
      "deck_id": "7694938",
      "path": "archive/deck-texts/pauper/7694938.json",
      "message": "Reused existing published deck-text blob."
    },
    {
      "scope": "deck-text",
      "status": "skipped",
      "format": "pauper",
      "deck_id": "7694939",
      "path": "archive/deck-texts/pauper/7694939.json",
      "message": "Reused existing published deck-text blob."
    },
    {
      "scope": "deck-text",
      "status": "skipped",
      "format": "pauper",
      "deck_id": "7694940",
      "path": "archive/deck-texts/pauper/7694940.json",
      "message": "Reused existing published deck-text blob."
    },
    {
      "scope": "deck-text",
      "status": "skipped",
      "format": "pauper",
      "deck_id": "7694941",
      "path": "archive/deck-texts/pauper/7694941.json",
      "message": "Reused existing published deck-text blob."
    },
    {
      "scope": "deck-text",
      "status": "skipped",
      "format": "pauper",
      "deck_id": "7694942",
      "path": "archive/deck-texts/pauper/7694942.json",
      "message": "Reused existing published deck-text blob."
    },
    {
      "scope": "deck-text",
      "status": "skipped",
      "format": "pauper",
      "deck_id": "7694943",
      "path": "archive/deck-texts/pauper/7694943.json",
      "message": "Reused existing published deck-text blob."
    },
    {
      "scope": "deck-text",
      "status": "skipped",
      "format": "pauper",
      "deck_id": "7694944",
      "path": "archive/deck-texts/pauper/7694944.json",
      "message": "Reused existing published deck-text blob."
    },
    {
      "scope": "deck-text",
      "status": "skipped",
      "format": "pauper",
      "deck_id": "7694945",
      "path": "archive/deck-texts/pauper/7694945.json",
      "message": "Reused existing published deck-text blob."
    },
    {
      "scope": "deck-text",
      "status": "skipped",
      "format": "pauper",
      "deck_id": "7694946",
      "path": "archive/deck-texts/pauper/7694946.json",
      "message": "Reused existing published deck-text blob."
    },
    {
      "scope": "deck-text",
      "status": "skipped",
      "format": "pauper",
      "deck_id": "7694947",
      "path": "archive/deck-texts/pauper/7694947.json",
      "message": "Reused existing published deck-text blob."
    },
    {
      "scope": "deck-text",
      "status": "skipped",
      "format": "pauper",
      "deck_id": "7694948",
      "path": "archive/deck-texts/pauper/7694948.json",
      "message": "Reused existing published deck-text blob."
    },
    {
      "scope": "deck-text",
      "status": "skipped",
      "format": "pauper",
      "deck_id": "7694949",
      "path": "archive/deck-texts/pauper/7694949.json",
      "message": "Reused existing published deck-text blob."
    },
    {
      "scope": "deck-text",
      "status": "skipped",
      "format": "pauper",
      "deck_id": "7694950",
      "path": "archive/deck-texts/pauper/7694950.json",
      "message": "Reused existing published deck-text blob."
    },
    {
      "scope": "deck-text",
      "status": "skipped",
      "format": "pauper",
      "deck_id": "7694951",
      "path": "archive/deck-texts/pauper/7694951.json",
      "message": "Reused existing published deck-text blob."
    },
    {
      "scope": "deck-text",
      "status": "skipped",
      "format": "pauper",
      "deck_id": "7694952",
      "path": "archive/deck-texts/pauper/7694952.json",
      "message": "Reused existing published deck-text blob."
    },
    {
      "scope": "deck-text",
      "status": "skipped",
      "format": "pauper",
      "deck_id": "7694953",
      "path": "archive/deck-texts/pauper/7694953.json",
      "message": "Reused existing published deck-text blob."
    },
    {
      "scope": "deck-text",
      "status": "skipped",
      "format": "pauper",
      "deck_id": "7694954",
      "path": "archive/deck-texts/pauper/7694954.json",
      "message": "Reused existing published deck-text blob."
    },
    {
      "scope": "deck-text",
      "status": "skipped",
      "format": "pauper",
      "deck_id": "7694955",
      "path": "archive/deck-texts/pauper/7694955.json",
      "message": "Reused existing published deck-text blob."
    },
    {
      "scope": "deck-text",
      "status": "skipped",
      "format": "pauper",
      "deck_id": "7694956",
      "path": "archive/deck-texts/pauper/7694956.json",
      "message": "Reused existing published deck-text blob."
    },
    {
      "scope": "deck-text",
      "status": "skipped",
      "format": "pauper",
      "deck_id": "7694957",
      "path": "archive/deck-texts/pauper/7694957.json",
      "message": "Reused existing published deck-text blob."
    },
    {
      "scope": "deck-text",
      "status": "skipped",
      "format": "pauper",
      "deck_id": "7694958",
      "path": "archive/deck-texts/pauper/7694958.json",
      "message": "Reused existing published deck-text blob."
    },
    {
      "scope": "deck-text",
      "status": "skipped",
      "format": "pauper",
      "deck_id": "7694959",
      "path": "archive/deck-texts/pauper/7694959.json",
      "message": "Reused existing published deck-text blob."
    },
    {
      "scope": "deck-text",
      "status": "skipped",
      "format": "pauper",
      "deck_id": "7694960",
      "path": "archive/deck-texts/pauper/7694960.json",
      "message": "Reused existing published deck-text blob."
    },
    {
      "scope": "deck-text",
      "status": "skipped",
      "format": "pauper",
      "deck_id": "7694961",
      "path": "archive/deck-texts/pauper/7694961.json",
      "message": "Reused existing published deck-text blob."
    },
    {
      "scope": "deck-text",
      "status": "skipped",
      "format": "pauper",
      "deck_id": "7694962",
      "path": "archive/deck-texts/pauper/7694962.json",
      "message": "Reused existing published deck-text blob."
    },
    {
      "scope": "deck-text",
      "status": "skipped",
      "format": "pauper",
      "deck_id": "7695150",
      "path": "archive/deck-texts/pauper/7695150.json",
      "message": "Reused existing published deck-text blob."
    },
    {
      "scope": "deck-text",
      "status": "skipped",
      "format": "pauper",
      "deck_id": "7695300",
      "path": "archive/deck-texts/pauper/7695300.json",
      "message": "Reused existing published deck-text blob."
    },
    {
      "scope": "deck-text",
      "status": "skipped",
      "format": "pauper",
      "deck_id": "7695301",
      "path": "archive/deck-texts/pauper/7695301.json",
      "message": "Reused existing published deck-text blob."
    },
    {
      "scope": "deck-text",
      "status": "skipped",
      "format": "pauper",
      "deck_id": "7695302",
      "path": "archive/deck-texts/pauper/7695302.json",
      "message": "Reused existing published deck-text blob."
    },
    {
      "scope": "deck-text",
      "status": "skipped",
      "format": "pauper",
      "deck_id": "7695303",
      "path": "archive/deck-texts/pauper/7695303.json",
      "message": "Reused existing published deck-text blob."
    },
    {
      "scope": "deck-text",
      "status": "skipped",
      "format": "pauper",
      "deck_id": "7695455",
      "path": "archive/deck-texts/pauper/7695455.json",
      "message": "Reused existing published deck-text blob."
    },
    {
      "scope": "deck-text",
      "status": "skipped",
      "format": "pauper",
      "deck_id": "7695456",
      "path": "archive/deck-texts/pauper/7695456.json",
      "message": "Reused existing published deck-text blob."
    },
    {
      "scope": "deck-text",
      "status": "skipped",
      "format": "pauper",
      "deck_id": "7695537",
      "path": "archive/deck-texts/pauper/7695537.json",
      "message": "Reused existing published deck-text blob."
    },
    {
      "scope": "deck-text",
      "status": "skipped",
      "format": "pauper",
      "deck_id": "7695763",
      "path": "archive/deck-texts/pauper/7695763.json",
      "message": "Reused existing published deck-text blob."
    },
    {
      "scope": "deck-text",
      "status": "skipped",
      "format": "pauper",
      "deck_id": "7695865",
      "path": "archive/deck-texts/pauper/7695865.json",
      "message": "Reused existing published deck-text blob."
    },
    {
      "scope": "deck-text",
      "status": "skipped",
      "format": "pauper",
      "deck_id": "7695866",
      "path": "archive/deck-texts/pauper/7695866.json",
      "message": "Reused existing published deck-text blob."
    },
    {
      "scope": "deck-text",
      "status": "skipped",
      "format": "pauper",
      "deck_id": "7695906",
      "path": "archive/deck-texts/pauper/7695906.json",
      "message": "Reused existing published deck-text blob."
    },
    {
      "scope": "deck-text",
      "status": "skipped",
      "format": "pauper",
      "deck_id": "7695907",
      "path": "archive/deck-texts/pauper/7695907.json",
      "message": "Reused existing published deck-text blob."
    },
    {
      "scope": "deck-text",
      "status": "skipped",
      "format": "pauper",
      "deck_id": "7695908",
      "path": "archive/deck-texts/pauper/7695908.json",
      "message": "Reused existing published deck-text blob."
    },
    {
      "scope": "deck-text",
      "status": "skipped",
      "format": "pauper",
      "deck_id": "7695909",
      "path": "archive/deck-texts/pauper/7695909.json",
      "message": "Reused existing published deck-text blob."
    },
    {
      "scope": "deck-text",
      "status": "skipped",
      "format": "pauper",
      "deck_id": "7695910",
      "path": "archive/deck-texts/pauper/7695910.json",
      "message": "Reused existing published deck-text blob."
    },
    {
      "scope": "deck-text",
      "status": "skipped",
      "format": "pauper",
      "deck_id": "7695911",
      "path": "archive/deck-texts/pauper/7695911.json",
      "message": "Reused existing published deck-text blob."
    },
    {
      "scope": "deck-text",
      "status": "skipped",
      "format": "pauper",
      "deck_id": "7695912",
      "path": "archive/deck-texts/pauper/7695912.json",
      "message": "Reused existing published deck-text blob."
    },
    {
      "scope": "deck-text",
      "status": "skipped",
      "format": "pauper",
      "deck_id": "7695913",
      "path": "archive/deck-texts/pauper/7695913.json",
      "message": "Reused existing published deck-text blob."
    },
    {
      "scope": "deck-text",
      "status": "skipped",
      "format": "pauper",
      "deck_id": "7695914",
      "path": "archive/deck-texts/pauper/7695914.json",
      "message": "Reused existing published deck-text blob."
    },
    {
      "scope": "deck-text",
      "status": "skipped",
      "format": "pauper",
      "deck_id": "7695921",
      "path": "archive/deck-texts/pauper/7695921.json",
      "message": "Reused existing published deck-text blob."
    },
    {
      "scope": "deck-text",
      "status": "skipped",
      "format": "pauper",
      "deck_id": "7695923",
      "path": "archive/deck-texts/pauper/7695923.json",
      "message": "Reused existing published deck-text blob."
    },
    {
      "scope": "deck-text",
      "status": "skipped",
      "format": "pauper",
      "deck_id": "7695925",
      "path": "archive/deck-texts/pauper/7695925.json",
      "message": "Reused existing published deck-text blob."
    },
    {
      "scope": "deck-text",
      "status": "skipped",
      "format": "pauper",
      "deck_id": "7695926",
      "path": "archive/deck-texts/pauper/7695926.json",
      "message": "Reused existing published deck-text blob."
    },
    {
      "scope": "deck-text",
      "status": "skipped",
      "format": "pauper",
      "deck_id": "7695927",
      "path": "archive/deck-texts/pauper/7695927.json",
      "message": "Reused existing published deck-text blob."
    },
    {
      "scope": "deck-text",
      "status": "skipped",
      "format": "pauper",
      "deck_id": "7695928",
      "path": "archive/deck-texts/pauper/7695928.json",
      "message": "Reused existing published deck-text blob."
    },
    {
      "scope": "deck-text",
      "status": "skipped",
      "format": "pauper",
      "deck_id": "7695929",
      "path": "archive/deck-texts/pauper/7695929.json",
      "message": "Reused existing published deck-text blob."
    },
    {
      "scope": "deck-text",
      "status": "skipped",
      "format": "pauper",
      "deck_id": "7695930",
      "path": "archive/deck-texts/pauper/7695930.json",
      "message": "Reused existing published deck-text blob."
    },
    {
      "scope": "deck-text",
      "status": "skipped",
      "format": "pauper",
      "deck_id": "7695931",
      "path": "archive/deck-texts/pauper/7695931.json",
      "message": "Reused existing published deck-text blob."
    },
    {
      "scope": "deck-text",
      "status": "skipped",
      "format": "pauper",
      "deck_id": "7695932",
      "path": "archive/deck-texts/pauper/7695932.json",
      "message": "Reused existing published deck-text blob."
    },
    {
      "scope": "deck-text",
      "status": "skipped",
      "format": "pauper",
      "deck_id": "7695933",
      "path": "archive/deck-texts/pauper/7695933.json",
      "message": "Reused existing published deck-text blob."
    },
    {
      "scope": "deck-text",
      "status": "skipped",
      "format": "pauper",
      "deck_id": "7695934",
      "path": "archive/deck-texts/pauper/7695934.json",
      "message": "Reused existing published deck-text blob."
    },
    {
      "scope": "deck-text",
      "status": "skipped",
      "format": "pauper",
      "deck_id": "7695935",
      "path": "archive/deck-texts/pauper/7695935.json",
      "message": "Reused existing published deck-text blob."
    },
    {
      "scope": "deck-text",
      "status": "skipped",
      "format": "pauper",
      "deck_id": "7695936",
      "path": "archive/deck-texts/pauper/7695936.json",
      "message": "Reused existing published deck-text blob."
    },
    {
      "scope": "deck-text",
      "status": "skipped",
      "format": "pauper",
      "deck_id": "7695937",
      "path": "archive/deck-texts/pauper/7695937.json",
      "message": "Reused existing published deck-text blob."
    },
    {
      "scope": "deck-text",
      "status": "skipped",
      "format": "pauper",
      "deck_id": "7695938",
      "path": "archive/deck-texts/pauper/7695938.json",
      "message": "Reused existing published deck-text blob."
    },
    {
      "scope": "deck-text",
      "status": "skipped",
      "format": "pauper",
      "deck_id": "7695939",
      "path": "archive/deck-texts/pauper/7695939.json",
      "message": "Reused existing published deck-text blob."
    },
    {
      "scope": "deck-text",
      "status": "skipped",
      "format": "pauper",
      "deck_id": "7695940",
      "path": "archive/deck-texts/pauper/7695940.json",
      "message": "Reused existing published deck-text blob."
    },
    {
      "scope": "deck-text",
      "status": "skipped",
      "format": "pauper",
      "deck_id": "7695941",
      "path": "archive/deck-texts/pauper/7695941.json",
      "message": "Reused existing published deck-text blob."
    },
    {
      "scope": "deck-text",
      "status": "skipped",
      "format": "pauper",
      "deck_id": "7695942",
      "path": "archive/deck-texts/pauper/7695942.json",
      "message": "Reused existing published deck-text blob."
    },
    {
      "scope": "deck-text",
      "status": "skipped",
      "format": "pauper",
      "deck_id": "7695943",
      "path": "archive/deck-texts/pauper/7695943.json",
      "message": "Reused existing published deck-text blob."
    },
    {
      "scope": "deck-text",
      "status": "skipped",
      "format": "pauper",
      "deck_id": "7695944",
      "path": "archive/deck-texts/pauper/7695944.json",
      "message": "Reused existing published deck-text blob."
    },
    {
      "scope": "deck-text",
      "status": "skipped",
      "format": "pauper",
      "deck_id": "7695945",
      "path": "archive/deck-texts/pauper/7695945.json",
      "message": "Reused existing published deck-text blob."
    },
    {
      "scope": "deck-text",
      "status": "skipped",
      "format": "pauper",
      "deck_id": "7695946",
      "path": "archive/deck-texts/pauper/7695946.json",
      "message": "Reused existing published deck-text blob."
    },
    {
      "scope": "deck-text",
      "status": "skipped",
      "format": "pauper",
      "deck_id": "7695947",
      "path": "archive/deck-texts/pauper/7695947.json",
      "message": "Reused existing published deck-text blob."
    },
    {
      "scope": "deck-text",
      "status": "skipped",
      "format": "pauper",
      "deck_id": "7695948",
      "path": "archive/deck-texts/pauper/7695948.json",
      "message": "Reused existing published deck-text blob."
    },
    {
      "scope": "deck-text",
      "status": "skipped",
      "format": "pauper",
      "deck_id": "7695949",
      "path": "archive/deck-texts/pauper/7695949.json",
      "message": "Reused existing published deck-text blob."
    },
    {
      "scope": "deck-text",
      "status": "skipped",
      "format": "pauper",
      "deck_id": "7695950",
      "path": "archive/deck-texts/pauper/7695950.json",
      "message": "Reused existing published deck-text blob."
    },
    {
      "scope": "deck-text",
      "status": "skipped",
      "format": "pauper",
      "deck_id": "7695951",
      "path": "archive/deck-texts/pauper/7695951.json",
      "message": "Reused existing published deck-text blob."
    },
    {
      "scope": "deck-text",
      "status": "skipped",
      "format": "pauper",
      "deck_id": "7695953",
      "path": "archive/deck-texts/pauper/7695953.json",
      "message": "Reused existing published deck-text blob."
    },
    {
      "scope": "deck-text",
      "status": "skipped",
      "format": "pauper",
      "deck_id": "7695954",
      "path": "archive/deck-texts/pauper/7695954.json",
      "message": "Reused existing published deck-text blob."
    },
    {
      "scope": "deck-text",
      "status": "skipped",
      "format": "pauper",
      "deck_id": "7695955",
      "path": "archive/deck-texts/pauper/7695955.json",
      "message": "Reused existing published deck-text blob."
    },
    {
      "scope": "deck-text",
      "status": "skipped",
      "format": "pauper",
      "deck_id": "7695956",
      "path": "archive/deck-texts/pauper/7695956.json",
      "message": "Reused existing published deck-text blob."
    },
    {
      "scope": "deck-text",
      "status": "skipped",
      "format": "pauper",
      "deck_id": "7695957",
      "path": "archive/deck-texts/pauper/7695957.json",
      "message": "Reused existing published deck-text blob."
    },
    {
      "scope": "deck-text",
      "status": "skipped",
      "format": "pauper",
      "deck_id": "7695958",
      "path": "archive/deck-texts/pauper/7695958.json",
      "message": "Reused existing published deck-text blob."
    },
    {
      "scope": "deck-text",
      "status": "skipped",
      "format": "pauper",
      "deck_id": "7695959",
      "path": "archive/deck-texts/pauper/7695959.json",
      "message": "Reused existing published deck-text blob."
    },
    {
      "scope": "deck-text",
      "status": "skipped",
      "format": "pauper",
      "deck_id": "7695960",
      "path": "archive/deck-texts/pauper/7695960.json",
      "message": "Reused existing published deck-text blob."
    },
    {
      "scope": "deck-text",
      "status": "skipped",
      "format": "pauper",
      "deck_id": "7695961",
      "path": "archive/deck-texts/pauper/7695961.json",
      "message": "Reused existing published deck-text blob."
    },
    {
      "scope": "deck-text",
      "status": "skipped",
      "format": "pauper",
      "deck_id": "7695963",
      "path": "archive/deck-texts/pauper/7695963.json",
      "message": "Reused existing published deck-text blob."
    },
    {
      "scope": "deck-text",
      "status": "skipped",
      "format": "pauper",
      "deck_id": "7695964",
      "path": "archive/deck-texts/pauper/7695964.json",
      "message": "Reused existing published deck-text blob."
    },
    {
      "scope": "deck-text",
      "status": "skipped",
      "format": "pauper",
      "deck_id": "7695965",
      "path": "archive/deck-texts/pauper/7695965.json",
      "message": "Reused existing published deck-text blob."
    },
    {
      "scope": "deck-text",
      "status": "skipped",
      "format": "pauper",
      "deck_id": "7695966",
      "path": "archive/deck-texts/pauper/7695966.json",
      "message": "Reused existing published deck-text blob."
    },
    {
      "scope": "deck-text",
      "status": "skipped",
      "format": "pauper",
      "deck_id": "7695968",
      "path": "archive/deck-texts/pauper/7695968.json",
      "message": "Reused existing published deck-text blob."
    },
    {
      "scope": "deck-text",
      "status": "skipped",
      "format": "pauper",
      "deck_id": "7695969",
      "path": "archive/deck-texts/pauper/7695969.json",
      "message": "Reused existing published deck-text blob."
    },
    {
      "scope": "deck-text",
      "status": "skipped",
      "format": "pauper",
      "deck_id": "7695970",
      "path": "archive/deck-texts/pauper/7695970.json",
      "message": "Reused existing published deck-text blob."
    },
    {
      "scope": "deck-text",
      "status": "skipped",
      "format": "pauper",
      "deck_id": "7695971",
      "path": "archive/deck-texts/pauper/7695971.json",
      "message": "Reused existing published deck-text blob."
    },
    {
      "scope": "deck-text",
      "status": "skipped",
      "format": "pauper",
      "deck_id": "7695972",
      "path": "archive/deck-texts/pauper/7695972.json",
      "message": "Reused existing published deck-text blob."
    },
    {
      "scope": "deck-text",
      "status": "skipped",
      "format": "pauper",
      "deck_id": "7695973",
      "path": "archive/deck-texts/pauper/7695973.json",
      "message": "Reused existing published deck-text blob."
    },
    {
      "scope": "deck-text",
      "status": "skipped",
      "format": "pauper",
      "deck_id": "7695974",
      "path": "archive/deck-texts/pauper/7695974.json",
      "message": "Reused existing published deck-text blob."
    },
    {
      "scope": "deck-text",
      "status": "skipped",
      "format": "pauper",
      "deck_id": "7695975",
      "path": "archive/deck-texts/pauper/7695975.json",
      "message": "Reused existing published deck-text blob."
    },
    {
      "scope": "deck-text",
      "status": "skipped",
      "format": "pauper",
      "deck_id": "7695977",
      "path": "archive/deck-texts/pauper/7695977.json",
      "message": "Reused existing published deck-text blob."
    },
    {
      "scope": "deck-text",
      "status": "skipped",
      "format": "pauper",
      "deck_id": "7695978",
      "path": "archive/deck-texts/pauper/7695978.json",
      "message": "Reused existing published deck-text blob."
    },
    {
      "scope": "deck-text",
      "status": "skipped",
      "format": "pauper",
      "deck_id": "7695979",
      "path": "archive/deck-texts/pauper/7695979.json",
      "message": "Reused existing published deck-text blob."
    },
    {
      "scope": "deck-text",
      "status": "skipped",
      "format": "pauper",
      "deck_id": "7695980",
      "path": "archive/deck-texts/pauper/7695980.json",
      "message": "Reused existing published deck-text blob."
    },
    {
      "scope": "deck-text",
      "status": "skipped",
      "format": "pauper",
      "deck_id": "7695981",
      "path": "archive/deck-texts/pauper/7695981.json",
      "message": "Reused existing published deck-text blob."
    },
    {
      "scope": "deck-text",
      "status": "skipped",
      "format": "pauper",
      "deck_id": "7695982",
      "path": "archive/deck-texts/pauper/7695982.json",
      "message": "Reused existing published deck-text blob."
    },
    {
      "scope": "deck-text",
      "status": "skipped",
      "format": "pauper",
      "deck_id": "7695983",
      "path": "archive/deck-texts/pauper/7695983.json",
      "message": "Reused existing published deck-text blob."
    },
    {
      "scope": "deck-text",
      "status": "skipped",
      "format": "pauper",
      "deck_id": "7695984",
      "path": "archive/deck-texts/pauper/7695984.json",
      "message": "Reused existing published deck-text blob."
    },
    {
      "scope": "deck-text",
      "status": "skipped",
      "format": "pauper",
      "deck_id": "7695985",
      "path": "archive/deck-texts/pauper/7695985.json",
      "message": "Reused existing published deck-text blob."
    },
    {
      "scope": "deck-text",
      "status": "skipped",
      "format": "pauper",
      "deck_id": "7695986",
      "path": "archive/deck-texts/pauper/7695986.json",
      "message": "Reused existing published deck-text blob."
    },
    {
      "scope": "deck-text",
      "status": "skipped",
      "format": "pauper",
      "deck_id": "7695987",
      "path": "archive/deck-texts/pauper/7695987.json",
      "message": "Reused existing published deck-text blob."
    },
    {
      "scope": "deck-text",
      "status": "skipped",
      "format": "pauper",
      "deck_id": "7695988",
      "path": "archive/deck-texts/pauper/7695988.json",
      "message": "Reused existing published deck-text blob."
    },
    {
      "scope": "deck-text",
      "status": "skipped",
      "format": "pauper",
      "deck_id": "7695989",
      "path": "archive/deck-texts/pauper/7695989.json",
      "message": "Reused existing published deck-text blob."
    },
    {
      "scope": "deck-text",
      "status": "skipped",
      "format": "pauper",
      "deck_id": "7695990",
      "path": "archive/deck-texts/pauper/7695990.json",
      "message": "Reused existing published deck-text blob."
    },
    {
      "scope": "deck-text",
      "status": "skipped",
      "format": "pauper",
      "deck_id": "7695991",
      "path": "archive/deck-texts/pauper/7695991.json",
      "message": "Reused existing published deck-text blob."
    },
    {
      "scope": "deck-text",
      "status": "skipped",
      "format": "pauper",
      "deck_id": "7695993",
      "path": "archive/deck-texts/pauper/7695993.json",
      "message": "Reused existing published deck-text blob."
    },
    {
      "scope": "deck-text",
      "status": "skipped",
      "format": "pauper",
      "deck_id": "7697391",
      "path": "archive/deck-texts/pauper/7697391.json",
      "message": "Reused existing published deck-text blob."
    },
    {
      "scope": "deck-text",
      "status": "skipped",
      "format": "pauper",
      "deck_id": "7697392",
      "path": "archive/deck-texts/pauper/7697392.json",
      "message": "Reused existing published deck-text blob."
    },
    {
      "scope": "deck-text",
      "status": "skipped",
      "format": "pauper",
      "deck_id": "7697393",
      "path": "archive/deck-texts/pauper/7697393.json",
      "message": "Reused existing published deck-text blob."
    },
    {
      "scope": "deck-text",
      "status": "skipped",
      "format": "pauper",
      "deck_id": "7697394",
      "path": "archive/deck-texts/pauper/7697394.json",
      "message": "Reused existing published deck-text blob."
    },
    {
      "scope": "deck-text",
      "status": "skipped",
      "format": "pauper",
      "deck_id": "7697781",
      "path": "archive/deck-texts/pauper/7697781.json",
      "message": "Reused existing published deck-text blob."
    },
    {
      "scope": "deck-text",
      "status": "skipped",
      "format": "pauper",
      "deck_id": "7697866",
      "path": "archive/deck-texts/pauper/7697866.json",
      "message": "Reused existing published deck-text blob."
    },
    {
      "scope": "deck-text",
      "status": "skipped",
      "format": "pauper",
      "deck_id": "7697875",
      "path": "archive/deck-texts/pauper/7697875.json",
      "message": "Reused existing published deck-text blob."
    },
    {
      "scope": "deck-text",
      "status": "skipped",
      "format": "pauper",
      "deck_id": "7697905",
      "path": "archive/deck-texts/pauper/7697905.json",
      "message": "Reused existing published deck-text blob."
    },
    {
      "scope": "deck-text",
      "status": "skipped",
      "format": "pauper",
      "deck_id": "7697970",
      "path": "archive/deck-texts/pauper/7697970.json",
      "message": "Reused existing published deck-text blob."
    },
    {
      "scope": "deck-text",
      "status": "skipped",
      "format": "pauper",
      "deck_id": "7697971",
      "path": "archive/deck-texts/pauper/7697971.json",
      "message": "Reused existing published deck-text blob."
    },
    {
      "scope": "deck-text",
      "status": "skipped",
      "format": "pauper",
      "deck_id": "7698099",
      "path": "archive/deck-texts/pauper/7698099.json",
      "message": "Reused existing published deck-text blob."
    },
    {
      "scope": "deck-text",
      "status": "skipped",
      "format": "pauper",
      "deck_id": "7698100",
      "path": "archive/deck-texts/pauper/7698100.json",
      "message": "Reused existing published deck-text blob."
    },
    {
      "scope": "deck-text",
      "status": "skipped",
      "format": "pauper",
      "deck_id": "7698176",
      "path": "archive/deck-texts/pauper/7698176.json",
      "message": "Reused existing published deck-text blob."
    },
    {
      "scope": "deck-text",
      "status": "skipped",
      "format": "pauper",
      "deck_id": "7698177",
      "path": "archive/deck-texts/pauper/7698177.json",
      "message": "Reused existing published deck-text blob."
    },
    {
      "scope": "deck-text",
      "status": "skipped",
      "format": "pauper",
      "deck_id": "7698178",
      "path": "archive/deck-texts/pauper/7698178.json",
      "message": "Reused existing published deck-text blob."
    },
    {
      "scope": "deck-text",
      "status": "skipped",
      "format": "pauper",
      "deck_id": "7698232",
      "path": "archive/deck-texts/pauper/7698232.json",
      "message": "Reused existing published deck-text blob."
    },
    {
      "scope": "deck-text",
      "status": "skipped",
      "format": "pauper",
      "deck_id": "7698301",
      "path": "archive/deck-texts/pauper/7698301.json",
      "message": "Reused existing published deck-text blob."
    },
    {
      "scope": "deck-text",
      "status": "skipped",
      "format": "pauper",
      "deck_id": "7698523",
      "path": "archive/deck-texts/pauper/7698523.json",
      "message": "Reused existing published deck-text blob."
    },
    {
      "scope": "deck-text",
      "status": "skipped",
      "format": "pauper",
      "deck_id": "7698524",
      "path": "archive/deck-texts/pauper/7698524.json",
      "message": "Reused existing published deck-text blob."
    },
    {
      "scope": "deck-text",
      "status": "skipped",
      "format": "pauper",
      "deck_id": "7698582",
      "path": "archive/deck-texts/pauper/7698582.json",
      "message": "Reused existing published deck-text blob."
    },
    {
      "scope": "deck-text",
      "status": "skipped",
      "format": "pauper",
      "deck_id": "7698719",
      "path": "archive/deck-texts/pauper/7698719.json",
      "message": "Reused existing published deck-text blob."
    },
    {
      "scope": "deck-text",
      "status": "skipped",
      "format": "pauper",
      "deck_id": "7698836",
      "path": "archive/deck-texts/pauper/7698836.json",
      "message": "Reused existing published deck-text blob."
    },
    {
      "scope": "deck-text",
      "status": "skipped",
      "format": "pauper",
      "deck_id": "7698927",
      "path": "archive/deck-texts/pauper/7698927.json",
      "message": "Reused existing published deck-text blob."
    },
    {
      "scope": "deck-text",
      "status": "skipped",
      "format": "pauper",
      "deck_id": "7698928",
      "path": "archive/deck-texts/pauper/7698928.json",
      "message": "Reused existing published deck-text blob."
    },
    {
      "scope": "deck-text",
      "status": "skipped",
      "format": "pauper",
      "deck_id": "7698929",
      "path": "archive/deck-texts/pauper/7698929.json",
      "message": "Reused existing published deck-text blob."
    },
    {
      "scope": "deck-text",
      "status": "skipped",
      "format": "pauper",
      "deck_id": "7699217",
      "path": "archive/deck-texts/pauper/7699217.json",
      "message": "Reused existing published deck-text blob."
    },
    {
      "scope": "deck-text",
      "status": "skipped",
      "format": "pauper",
      "deck_id": "7699218",
      "path": "archive/deck-texts/pauper/7699218.json",
      "message": "Reused existing published deck-text blob."
    },
    {
      "scope": "deck-text",
      "status": "skipped",
      "format": "pauper",
      "deck_id": "7699219",
      "path": "archive/deck-texts/pauper/7699219.json",
      "message": "Reused existing published deck-text blob."
    },
    {
      "scope": "deck-text",
      "status": "skipped",
      "format": "pauper",
      "deck_id": "7699220",
      "path": "archive/deck-texts/pauper/7699220.json",
      "message": "Reused existing published deck-text blob."
    },
    {
      "scope": "deck-text",
      "status": "skipped",
      "format": "pauper",
      "deck_id": "7699269",
      "path": "archive/deck-texts/pauper/7699269.json",
      "message": "Reused existing published deck-text blob."
    },
    {
      "scope": "deck-text",
      "status": "skipped",
      "format": "pauper",
      "deck_id": "7699270",
      "path": "archive/deck-texts/pauper/7699270.json",
      "message": "Reused existing published deck-text blob."
    },
    {
      "scope": "deck-text",
      "status": "skipped",
      "format": "pauper",
      "deck_id": "7699425",
      "path": "archive/deck-texts/pauper/7699425.json",
      "message": "Reused existing published deck-text blob."
    },
    {
      "scope": "deck-text",
      "status": "skipped",
      "format": "pauper",
      "deck_id": "7699473",
      "path": "archive/deck-texts/pauper/7699473.json",
      "message": "Reused existing published deck-text blob."
    },
    {
      "scope": "deck-text",
      "status": "skipped",
      "format": "pauper",
      "deck_id": "7699532",
      "path": "archive/deck-texts/pauper/7699532.json",
      "message": "Reused existing published deck-text blob."
    },
    {
      "scope": "deck-text",
      "status": "skipped",
      "format": "pauper",
      "deck_id": "7699638",
      "path": "archive/deck-texts/pauper/7699638.json",
      "message": "Reused existing published deck-text blob."
    },
    {
      "scope": "deck-text",
      "status": "skipped",
      "format": "pauper",
      "deck_id": "7699639",
      "path": "archive/deck-texts/pauper/7699639.json",
      "message": "Reused existing published deck-text blob."
    },
    {
      "scope": "deck-text",
      "status": "skipped",
      "format": "pauper",
      "deck_id": "7699710",
      "path": "archive/deck-texts/pauper/7699710.json",
      "message": "Reused existing published deck-text blob."
    },
    {
      "scope": "deck-text",
      "status": "skipped",
      "format": "pauper",
      "deck_id": "7699711",
      "path": "archive/deck-texts/pauper/7699711.json",
      "message": "Reused existing published deck-text blob."
    },
    {
      "scope": "deck-text",
      "status": "skipped",
      "format": "pauper",
      "deck_id": "7700061",
      "path": "archive/deck-texts/pauper/7700061.json",
      "message": "Reused existing published deck-text blob."
    },
    {
      "scope": "deck-text",
      "status": "skipped",
      "format": "pauper",
      "deck_id": "7700062",
      "path": "archive/deck-texts/pauper/7700062.json",
      "message": "Reused existing published deck-text blob."
    },
    {
      "scope": "deck-text",
      "status": "skipped",
      "format": "pauper",
      "deck_id": "7700063",
      "path": "archive/deck-texts/pauper/7700063.json",
      "message": "Reused existing published deck-text blob."
    },
    {
      "scope": "deck-text",
      "status": "skipped",
      "format": "pauper",
      "deck_id": "7700106",
      "path": "archive/deck-texts/pauper/7700106.json",
      "message": "Reused existing published deck-text blob."
    },
    {
      "scope": "deck-text",
      "status": "skipped",
      "format": "pauper",
      "deck_id": "7700108",
      "path": "archive/deck-texts/pauper/7700108.json",
      "message": "Reused existing published deck-text blob."
    },
    {
      "scope": "deck-text",
      "status": "skipped",
      "format": "pauper",
      "deck_id": "7700165",
      "path": "archive/deck-texts/pauper/7700165.json",
      "message": "Reused existing published deck-text blob."
    },
    {
      "scope": "deck-text",
      "status": "skipped",
      "format": "pauper",
      "deck_id": "7700235",
      "path": "archive/deck-texts/pauper/7700235.json",
      "message": "Reused existing published deck-text blob."
    },
    {
      "scope": "deck-text",
      "status": "skipped",
      "format": "pauper",
      "deck_id": "7700236",
      "path": "archive/deck-texts/pauper/7700236.json",
      "message": "Reused existing published deck-text blob."
    },
    {
      "scope": "deck-text",
      "status": "skipped",
      "format": "pauper",
      "deck_id": "7700391",
      "path": "archive/deck-texts/pauper/7700391.json",
      "message": "Reused existing published deck-text blob."
    },
    {
      "scope": "deck-text",
      "status": "skipped",
      "format": "pauper",
      "deck_id": "7700392",
      "path": "archive/deck-texts/pauper/7700392.json",
      "message": "Reused existing published deck-text blob."
    },
    {
      "scope": "deck-text",
      "status": "skipped",
      "format": "pauper",
      "deck_id": "7700397",
      "path": "archive/deck-texts/pauper/7700397.json",
      "message": "Reused existing published deck-text blob."
    },
    {
      "scope": "deck-text",
      "status": "skipped",
      "format": "pauper",
      "deck_id": "7700431",
      "path": "archive/deck-texts/pauper/7700431.json",
      "message": "Reused existing published deck-text blob."
    },
    {
      "scope": "deck-text",
      "status": "skipped",
      "format": "pauper",
      "deck_id": "7700432",
      "path": "archive/deck-texts/pauper/7700432.json",
      "message": "Reused existing published deck-text blob."
    },
    {
      "scope": "deck-text",
      "status": "skipped",
      "format": "pauper",
      "deck_id": "7700560",
      "path": "archive/deck-texts/pauper/7700560.json",
      "message": "Reused existing published deck-text blob."
    },
    {
      "scope": "deck-text",
      "status": "skipped",
      "format": "pauper",
      "deck_id": "7700561",
      "path": "archive/deck-texts/pauper/7700561.json",
      "message": "Reused existing published deck-text blob."
    },
    {
      "scope": "deck-text",
      "status": "skipped",
      "format": "pauper",
      "deck_id": "7700562",
      "path": "archive/deck-texts/pauper/7700562.json",
      "message": "Reused existing published deck-text blob."
    },
    {
      "scope": "deck-text",
      "status": "skipped",
      "format": "pauper",
      "deck_id": "7700563",
      "path": "archive/deck-texts/pauper/7700563.json",
      "message": "Reused existing published deck-text blob."
    },
    {
      "scope": "deck-text",
      "status": "skipped",
      "format": "pauper",
      "deck_id": "7700564",
      "path": "archive/deck-texts/pauper/7700564.json",
      "message": "Reused existing published deck-text blob."
    },
    {
      "scope": "deck-text",
      "status": "skipped",
      "format": "pauper",
      "deck_id": "7700565",
      "path": "archive/deck-texts/pauper/7700565.json",
      "message": "Reused existing published deck-text blob."
    },
    {
      "scope": "deck-text",
      "status": "skipped",
      "format": "pauper",
      "deck_id": "7700566",
      "path": "archive/deck-texts/pauper/7700566.json",
      "message": "Reused existing published deck-text blob."
    },
    {
      "scope": "deck-text",
      "status": "skipped",
      "format": "pauper",
      "deck_id": "7700567",
      "path": "archive/deck-texts/pauper/7700567.json",
      "message": "Reused existing published deck-text blob."
    },
    {
      "scope": "deck-text",
      "status": "skipped",
      "format": "pauper",
      "deck_id": "7700568",
      "path": "archive/deck-texts/pauper/7700568.json",
      "message": "Reused existing published deck-text blob."
    },
    {
      "scope": "deck-text",
      "status": "skipped",
      "format": "pauper",
      "deck_id": "7700569",
      "path": "archive/deck-texts/pauper/7700569.json",
      "message": "Reused existing published deck-text blob."
    },
    {
      "scope": "deck-text",
      "status": "skipped",
      "format": "pauper",
      "deck_id": "7700570",
      "path": "archive/deck-texts/pauper/7700570.json",
      "message": "Reused existing published deck-text blob."
    },
    {
      "scope": "deck-text",
      "status": "skipped",
      "format": "pauper",
      "deck_id": "7700571",
      "path": "archive/deck-texts/pauper/7700571.json",
      "message": "Reused existing published deck-text blob."
    },
    {
      "scope": "deck-text",
      "status": "skipped",
      "format": "pauper",
      "deck_id": "7700572",
      "path": "archive/deck-texts/pauper/7700572.json",
      "message": "Reused existing published deck-text blob."
    },
    {
      "scope": "deck-text",
      "status": "skipped",
      "format": "pauper",
      "deck_id": "7700573",
      "path": "archive/deck-texts/pauper/7700573.json",
      "message": "Reused existing published deck-text blob."
    },
    {
      "scope": "deck-text",
      "status": "skipped",
      "format": "pauper",
      "deck_id": "7700574",
      "path": "archive/deck-texts/pauper/7700574.json",
      "message": "Reused existing published deck-text blob."
    },
    {
      "scope": "deck-text",
      "status": "skipped",
      "format": "pauper",
      "deck_id": "7700575",
      "path": "archive/deck-texts/pauper/7700575.json",
      "message": "Reused existing published deck-text blob."
    },
    {
      "scope": "deck-text",
      "status": "skipped",
      "format": "pauper",
      "deck_id": "7700576",
      "path": "archive/deck-texts/pauper/7700576.json",
      "message": "Reused existing published deck-text blob."
    },
    {
      "scope": "deck-text",
      "status": "skipped",
      "format": "pauper",
      "deck_id": "7700577",
      "path": "archive/deck-texts/pauper/7700577.json",
      "message": "Reused existing published deck-text blob."
    },
    {
      "scope": "deck-text",
      "status": "skipped",
      "format": "pauper",
      "deck_id": "7700578",
      "path": "archive/deck-texts/pauper/7700578.json",
      "message": "Reused existing published deck-text blob."
    },
    {
      "scope": "deck-text",
      "status": "skipped",
      "format": "pauper",
      "deck_id": "7700786",
      "path": "archive/deck-texts/pauper/7700786.json",
      "message": "Reused existing published deck-text blob."
    },
    {
      "scope": "deck-text",
      "status": "skipped",
      "format": "pauper",
      "deck_id": "7700787",
      "path": "archive/deck-texts/pauper/7700787.json",
      "message": "Reused existing published deck-text blob."
    },
    {
      "scope": "deck-text",
      "status": "skipped",
      "format": "pauper",
      "deck_id": "7700834",
      "path": "archive/deck-texts/pauper/7700834.json",
      "message": "Reused existing published deck-text blob."
    },
    {
      "scope": "deck-text",
      "status": "skipped",
      "format": "pauper",
      "deck_id": "7700835",
      "path": "archive/deck-texts/pauper/7700835.json",
      "message": "Reused existing published deck-text blob."
    },
    {
      "scope": "deck-text",
      "status": "skipped",
      "format": "pauper",
      "deck_id": "7700910",
      "path": "archive/deck-texts/pauper/7700910.json",
      "message": "Reused existing published deck-text blob."
    },
    {
      "scope": "deck-text",
      "status": "skipped",
      "format": "pauper",
      "deck_id": "7700955",
      "path": "archive/deck-texts/pauper/7700955.json",
      "message": "Reused existing published deck-text blob."
    },
    {
      "scope": "deck-text",
      "status": "skipped",
      "format": "pauper",
      "deck_id": "7700956",
      "path": "archive/deck-texts/pauper/7700956.json",
      "message": "Reused existing published deck-text blob."
    },
    {
      "scope": "deck-text",
      "status": "skipped",
      "format": "pauper",
      "deck_id": "7700957",
      "path": "archive/deck-texts/pauper/7700957.json",
      "message": "Reused existing published deck-text blob."
    },
    {
      "scope": "deck-text",
      "status": "skipped",
      "format": "pauper",
      "deck_id": "7701020",
      "path": "archive/deck-texts/pauper/7701020.json",
      "message": "Reused existing published deck-text blob."
    },
    {
      "scope": "deck-text",
      "status": "skipped",
      "format": "pauper",
      "deck_id": "7701079",
      "path": "archive/deck-texts/pauper/7701079.json",
      "message": "Reused existing published deck-text blob."
    },
    {
      "scope": "deck-text",
      "status": "skipped",
      "format": "pauper",
      "deck_id": "7701080",
      "path": "archive/deck-texts/pauper/7701080.json",
      "message": "Reused existing published deck-text blob."
    },
    {
      "scope": "deck-text",
      "status": "skipped",
      "format": "pauper",
      "deck_id": "7701087",
      "path": "archive/deck-texts/pauper/7701087.json",
      "message": "Reused existing published deck-text blob."
    },
    {
      "scope": "deck-text",
      "status": "skipped",
      "format": "pauper",
      "deck_id": "7701113",
      "path": "archive/deck-texts/pauper/7701113.json",
      "message": "Reused existing published deck-text blob."
    },
    {
      "scope": "deck-text",
      "status": "skipped",
      "format": "pauper",
      "deck_id": "7701142",
      "path": "archive/deck-texts/pauper/7701142.json",
      "message": "Reused existing published deck-text blob."
    },
    {
      "scope": "deck-text",
      "status": "skipped",
      "format": "pauper",
      "deck_id": "7701310",
      "path": "archive/deck-texts/pauper/7701310.json",
      "message": "Reused existing published deck-text blob."
    },
    {
      "scope": "deck-text",
      "status": "skipped",
      "format": "pauper",
      "deck_id": "7701582",
      "path": "archive/deck-texts/pauper/7701582.json",
      "message": "Reused existing published deck-text blob."
    },
    {
      "scope": "deck-text",
      "status": "skipped",
      "format": "pauper",
      "deck_id": "7701583",
      "path": "archive/deck-texts/pauper/7701583.json",
      "message": "Reused existing published deck-text blob."
    },
    {
      "scope": "deck-text",
      "status": "skipped",
      "format": "pauper",
      "deck_id": "7701750",
      "path": "archive/deck-texts/pauper/7701750.json",
      "message": "Reused existing published deck-text blob."
    },
    {
      "scope": "deck-text",
      "status": "skipped",
      "format": "pauper",
      "deck_id": "7701751",
      "path": "archive/deck-texts/pauper/7701751.json",
      "message": "Reused existing published deck-text blob."
    },
    {
      "scope": "deck-text",
      "status": "skipped",
      "format": "pauper",
      "deck_id": "7701833",
      "path": "archive/deck-texts/pauper/7701833.json",
      "message": "Reused existing published deck-text blob."
    },
    {
      "scope": "deck-text",
      "status": "skipped",
      "format": "pauper",
      "deck_id": "7702125",
      "path": "archive/deck-texts/pauper/7702125.json",
      "message": "Reused existing published deck-text blob."
    },
    {
      "scope": "deck-text",
      "status": "skipped",
      "format": "pauper",
      "deck_id": "7702142",
      "path": "archive/deck-texts/pauper/7702142.json",
      "message": "Reused existing published deck-text blob."
    },
    {
      "scope": "deck-text",
      "status": "skipped",
      "format": "pauper",
      "deck_id": "7702691",
      "path": "archive/deck-texts/pauper/7702691.json",
      "message": "Reused existing published deck-text blob."
    },
    {
      "scope": "deck-text",
      "status": "skipped",
      "format": "pauper",
      "deck_id": "7702693",
      "path": "archive/deck-texts/pauper/7702693.json",
      "message": "Reused existing published deck-text blob."
    },
    {
      "scope": "deck-text",
      "status": "skipped",
      "format": "pauper",
      "deck_id": "7702728",
      "path": "archive/deck-texts/pauper/7702728.json",
      "message": "Reused existing published deck-text blob."
    },
    {
      "scope": "deck-text",
      "status": "skipped",
      "format": "pauper",
      "deck_id": "7702729",
      "path": "archive/deck-texts/pauper/7702729.json",
      "message": "Reused existing published deck-text blob."
    },
    {
      "scope": "deck-text",
      "status": "skipped",
      "format": "pauper",
      "deck_id": "7702809",
      "path": "archive/deck-texts/pauper/7702809.json",
      "message": "Reused existing published deck-text blob."
    },
    {
      "scope": "deck-text",
      "status": "skipped",
      "format": "pauper",
      "deck_id": "7703007",
      "path": "archive/deck-texts/pauper/7703007.json",
      "message": "Reused existing published deck-text blob."
    },
    {
      "scope": "deck-text",
      "status": "skipped",
      "format": "pauper",
      "deck_id": "7703008",
      "path": "archive/deck-texts/pauper/7703008.json",
      "message": "Reused existing published deck-text blob."
    },
    {
      "scope": "deck-text",
      "status": "skipped",
      "format": "pauper",
      "deck_id": "7703067",
      "path": "archive/deck-texts/pauper/7703067.json",
      "message": "Reused existing published deck-text blob."
    },
    {
      "scope": "deck-text",
      "status": "skipped",
      "format": "pauper",
      "deck_id": "7703068",
      "path": "archive/deck-texts/pauper/7703068.json",
      "message": "Reused existing published deck-text blob."
    },
    {
      "scope": "deck-text",
      "status": "skipped",
      "format": "pauper",
      "deck_id": "7703069",
      "path": "archive/deck-texts/pauper/7703069.json",
      "message": "Reused existing published deck-text blob."
    },
    {
      "scope": "deck-text",
      "status": "skipped",
      "format": "pauper",
      "deck_id": "7703070",
      "path": "archive/deck-texts/pauper/7703070.json",
      "message": "Reused existing published deck-text blob."
    },
    {
      "scope": "deck-text",
      "status": "skipped",
      "format": "pauper",
      "deck_id": "7703071",
      "path": "archive/deck-texts/pauper/7703071.json",
      "message": "Reused existing published deck-text blob."
    },
    {
      "scope": "deck-text",
      "status": "skipped",
      "format": "pauper",
      "deck_id": "7703072",
      "path": "archive/deck-texts/pauper/7703072.json",
      "message": "Reused existing published deck-text blob."
    },
    {
      "scope": "deck-text",
      "status": "skipped",
      "format": "pauper",
      "deck_id": "7703073",
      "path": "archive/deck-texts/pauper/7703073.json",
      "message": "Reused existing published deck-text blob."
    },
    {
      "scope": "deck-text",
      "status": "skipped",
      "format": "pauper",
      "deck_id": "7703074",
      "path": "archive/deck-texts/pauper/7703074.json",
      "message": "Reused existing published deck-text blob."
    },
    {
      "scope": "deck-text",
      "status": "skipped",
      "format": "pauper",
      "deck_id": "7703075",
      "path": "archive/deck-texts/pauper/7703075.json",
      "message": "Reused existing published deck-text blob."
    },
    {
      "scope": "deck-text",
      "status": "skipped",
      "format": "pauper",
      "deck_id": "7703076",
      "path": "archive/deck-texts/pauper/7703076.json",
      "message": "Reused existing published deck-text blob."
    },
    {
      "scope": "deck-text",
      "status": "skipped",
      "format": "pauper",
      "deck_id": "7703077",
      "path": "archive/deck-texts/pauper/7703077.json",
      "message": "Reused existing published deck-text blob."
    },
    {
      "scope": "deck-text",
      "status": "skipped",
      "format": "pauper",
      "deck_id": "7703078",
      "path": "archive/deck-texts/pauper/7703078.json",
      "message": "Reused existing published deck-text blob."
    },
    {
      "scope": "deck-text",
      "status": "skipped",
      "format": "pauper",
      "deck_id": "7703079",
      "path": "archive/deck-texts/pauper/7703079.json",
      "message": "Reused existing published deck-text blob."
    },
    {
      "scope": "deck-text",
      "status": "skipped",
      "format": "pauper",
      "deck_id": "7703080",
      "path": "archive/deck-texts/pauper/7703080.json",
      "message": "Reused existing published deck-text blob."
    },
    {
      "scope": "deck-text",
      "status": "skipped",
      "format": "pauper",
      "deck_id": "7703081",
      "path": "archive/deck-texts/pauper/7703081.json",
      "message": "Reused existing published deck-text blob."
    },
    {
      "scope": "deck-text",
      "status": "skipped",
      "format": "pauper",
      "deck_id": "7703082",
      "path": "archive/deck-texts/pauper/7703082.json",
      "message": "Reused existing published deck-text blob."
    },
    {
      "scope": "deck-text",
      "status": "skipped",
      "format": "pauper",
      "deck_id": "7703083",
      "path": "archive/deck-texts/pauper/7703083.json",
      "message": "Reused existing published deck-text blob."
    },
    {
      "scope": "deck-text",
      "status": "skipped",
      "format": "pauper",
      "deck_id": "7703084",
      "path": "archive/deck-texts/pauper/7703084.json",
      "message": "Reused existing published deck-text blob."
    },
    {
      "scope": "deck-text",
      "status": "skipped",
      "format": "pauper",
      "deck_id": "7703085",
      "path": "archive/deck-texts/pauper/7703085.json",
      "message": "Reused existing published deck-text blob."
    },
    {
      "scope": "deck-text",
      "status": "skipped",
      "format": "pauper",
      "deck_id": "7703086",
      "path": "archive/deck-texts/pauper/7703086.json",
      "message": "Reused existing published deck-text blob."
    },
    {
      "scope": "deck-text",
      "status": "skipped",
      "format": "pauper",
      "deck_id": "7703087",
      "path": "archive/deck-texts/pauper/7703087.json",
      "message": "Reused existing published deck-text blob."
    },
    {
      "scope": "deck-text",
      "status": "skipped",
      "format": "pauper",
      "deck_id": "7703088",
      "path": "archive/deck-texts/pauper/7703088.json",
      "message": "Reused existing published deck-text blob."
    },
    {
      "scope": "deck-text",
      "status": "skipped",
      "format": "pauper",
      "deck_id": "7703089",
      "path": "archive/deck-texts/pauper/7703089.json",
      "message": "Reused existing published deck-text blob."
    },
    {
      "scope": "deck-text",
      "status": "skipped",
      "format": "pauper",
      "deck_id": "7703090",
      "path": "archive/deck-texts/pauper/7703090.json",
      "message": "Reused existing published deck-text blob."
    },
    {
      "scope": "deck-text",
      "status": "skipped",
      "format": "pauper",
      "deck_id": "7703091",
      "path": "archive/deck-texts/pauper/7703091.json",
      "message": "Reused existing published deck-text blob."
    },
    {
      "scope": "deck-text",
      "status": "skipped",
      "format": "pauper",
      "deck_id": "7703092",
      "path": "archive/deck-texts/pauper/7703092.json",
      "message": "Reused existing published deck-text blob."
    },
    {
      "scope": "deck-text",
      "status": "skipped",
      "format": "pauper",
      "deck_id": "7703093",
      "path": "archive/deck-texts/pauper/7703093.json",
      "message": "Reused existing published deck-text blob."
    },
    {
      "scope": "deck-text",
      "status": "skipped",
      "format": "pauper",
      "deck_id": "7703094",
      "path": "archive/deck-texts/pauper/7703094.json",
      "message": "Reused existing published deck-text blob."
    },
    {
      "scope": "deck-text",
      "status": "skipped",
      "format": "pauper",
      "deck_id": "7703096",
      "path": "archive/deck-texts/pauper/7703096.json",
      "message": "Reused existing published deck-text blob."
    },
    {
      "scope": "deck-text",
      "status": "skipped",
      "format": "pauper",
      "deck_id": "7703097",
      "path": "archive/deck-texts/pauper/7703097.json",
      "message": "Reused existing published deck-text blob."
    },
    {
      "scope": "deck-text",
      "status": "skipped",
      "format": "pauper",
      "deck_id": "7703122",
      "path": "archive/deck-texts/pauper/7703122.json",
      "message": "Reused existing published deck-text blob."
    },
    {
      "scope": "deck-text",
      "status": "skipped",
      "format": "pauper",
      "deck_id": "7703164",
      "path": "archive/deck-texts/pauper/7703164.json",
      "message": "Reused existing published deck-text blob."
    },
    {
      "scope": "deck-text",
      "status": "skipped",
      "format": "pauper",
      "deck_id": "7703165",
      "path": "archive/deck-texts/pauper/7703165.json",
      "message": "Reused existing published deck-text blob."
    },
    {
      "scope": "deck-text",
      "status": "skipped",
      "format": "pauper",
      "deck_id": "7703306",
      "path": "archive/deck-texts/pauper/7703306.json",
      "message": "Reused existing published deck-text blob."
    },
    {
      "scope": "deck-text",
      "status": "skipped",
      "format": "pauper",
      "deck_id": "7703493",
      "path": "archive/deck-texts/pauper/7703493.json",
      "message": "Reused existing published deck-text blob."
    },
    {
      "scope": "deck-text",
      "status": "skipped",
      "format": "pauper",
      "deck_id": "7703499",
      "path": "archive/deck-texts/pauper/7703499.json",
      "message": "Reused existing published deck-text blob."
    },
    {
      "scope": "deck-text",
      "status": "skipped",
      "format": "pauper",
      "deck_id": "7703625",
      "path": "archive/deck-texts/pauper/7703625.json",
      "message": "Reused existing published deck-text blob."
    },
    {
      "scope": "deck-text",
      "status": "skipped",
      "format": "pauper",
      "deck_id": "7703626",
      "path": "archive/deck-texts/pauper/7703626.json",
      "message": "Reused existing published deck-text blob."
    },
    {
      "scope": "deck-text",
      "status": "skipped",
      "format": "pauper",
      "deck_id": "7703627",
      "path": "archive/deck-texts/pauper/7703627.json",
      "message": "Reused existing published deck-text blob."
    },
    {
      "scope": "deck-text",
      "status": "skipped",
      "format": "pauper",
      "deck_id": "7703628",
      "path": "archive/deck-texts/pauper/7703628.json",
      "message": "Reused existing published deck-text blob."
    },
    {
      "scope": "deck-text",
      "status": "skipped",
      "format": "pauper",
      "deck_id": "7703740",
      "path": "archive/deck-texts/pauper/7703740.json",
      "message": "Reused existing published deck-text blob."
    },
    {
      "scope": "deck-text",
      "status": "skipped",
      "format": "pauper",
      "deck_id": "7703741",
      "path": "archive/deck-texts/pauper/7703741.json",
      "message": "Reused existing published deck-text blob."
    },
    {
      "scope": "deck-text",
      "status": "skipped",
      "format": "pauper",
      "deck_id": "7703908",
      "path": "archive/deck-texts/pauper/7703908.json",
      "message": "Reused existing published deck-text blob."
    },
    {
      "scope": "deck-text",
      "status": "skipped",
      "format": "pauper",
      "deck_id": "7703909",
      "path": "archive/deck-texts/pauper/7703909.json",
      "message": "Reused existing published deck-text blob."
    },
    {
      "scope": "deck-text",
      "status": "skipped",
      "format": "pauper",
      "deck_id": "7703910",
      "path": "archive/deck-texts/pauper/7703910.json",
      "message": "Reused existing published deck-text blob."
    },
    {
      "scope": "deck-text",
      "status": "skipped",
      "format": "pauper",
      "deck_id": "7704000",
      "path": "archive/deck-texts/pauper/7704000.json",
      "message": "Reused existing published deck-text blob."
    },
    {
      "scope": "deck-text",
      "status": "skipped",
      "format": "pauper",
      "deck_id": "7704001",
      "path": "archive/deck-texts/pauper/7704001.json",
      "message": "Reused existing published deck-text blob."
    },
    {
      "scope": "deck-text",
      "status": "skipped",
      "format": "pauper",
      "deck_id": "7704002",
      "path": "archive/deck-texts/pauper/7704002.json",
      "message": "Reused existing published deck-text blob."
    },
    {
      "scope": "deck-text",
      "status": "skipped",
      "format": "pauper",
      "deck_id": "7704054",
      "path": "archive/deck-texts/pauper/7704054.json",
      "message": "Reused existing published deck-text blob."
    },
    {
      "scope": "deck-text",
      "status": "skipped",
      "format": "pauper",
      "deck_id": "7704055",
      "path": "archive/deck-texts/pauper/7704055.json",
      "message": "Reused existing published deck-text blob."
    },
    {
      "scope": "deck-text",
      "status": "skipped",
      "format": "pauper",
      "deck_id": "7704056",
      "path": "archive/deck-texts/pauper/7704056.json",
      "message": "Reused existing published deck-text blob."
    },
    {
      "scope": "deck-text",
      "status": "skipped",
      "format": "pauper",
      "deck_id": "7704057",
      "path": "archive/deck-texts/pauper/7704057.json",
      "message": "Reused existing published deck-text blob."
    },
    {
      "scope": "deck-text",
      "status": "skipped",
      "format": "pauper",
      "deck_id": "7704058",
      "path": "archive/deck-texts/pauper/7704058.json",
      "message": "Reused existing published deck-text blob."
    },
    {
      "scope": "deck-text",
      "status": "skipped",
      "format": "pauper",
      "deck_id": "7704059",
      "path": "archive/deck-texts/pauper/7704059.json",
      "message": "Reused existing published deck-text blob."
    },
    {
      "scope": "deck-text",
      "status": "skipped",
      "format": "pauper",
      "deck_id": "7704060",
      "path": "archive/deck-texts/pauper/7704060.json",
      "message": "Reused existing published deck-text blob."
    },
    {
      "scope": "deck-text",
      "status": "skipped",
      "format": "pauper",
      "deck_id": "7704062",
      "path": "archive/deck-texts/pauper/7704062.json",
      "message": "Reused existing published deck-text blob."
    },
    {
      "scope": "deck-text",
      "status": "skipped",
      "format": "pauper",
      "deck_id": "7704063",
      "path": "archive/deck-texts/pauper/7704063.json",
      "message": "Reused existing published deck-text blob."
    },
    {
      "scope": "deck-text",
      "status": "skipped",
      "format": "pauper",
      "deck_id": "7704064",
      "path": "archive/deck-texts/pauper/7704064.json",
      "message": "Reused existing published deck-text blob."
    },
    {
      "scope": "deck-text",
      "status": "skipped",
      "format": "pauper",
      "deck_id": "7704065",
      "path": "archive/deck-texts/pauper/7704065.json",
      "message": "Reused existing published deck-text blob."
    },
    {
      "scope": "deck-text",
      "status": "skipped",
      "format": "pauper",
      "deck_id": "7704066",
      "path": "archive/deck-texts/pauper/7704066.json",
      "message": "Reused existing published deck-text blob."
    },
    {
      "scope": "deck-text",
      "status": "skipped",
      "format": "pauper",
      "deck_id": "7704067",
      "path": "archive/deck-texts/pauper/7704067.json",
      "message": "Reused existing published deck-text blob."
    },
    {
      "scope": "deck-text",
      "status": "skipped",
      "format": "pauper",
      "deck_id": "7704068",
      "path": "archive/deck-texts/pauper/7704068.json",
      "message": "Reused existing published deck-text blob."
    },
    {
      "scope": "deck-text",
      "status": "skipped",
      "format": "pauper",
      "deck_id": "7704069",
      "path": "archive/deck-texts/pauper/7704069.json",
      "message": "Reused existing published deck-text blob."
    },
    {
      "scope": "deck-text",
      "status": "skipped",
      "format": "pauper",
      "deck_id": "7704070",
      "path": "archive/deck-texts/pauper/7704070.json",
      "message": "Reused existing published deck-text blob."
    },
    {
      "scope": "deck-text",
      "status": "skipped",
      "format": "pauper",
      "deck_id": "7704071",
      "path": "archive/deck-texts/pauper/7704071.json",
      "message": "Reused existing published deck-text blob."
    },
    {
      "scope": "deck-text",
      "status": "skipped",
      "format": "pauper",
      "deck_id": "7704072",
      "path": "archive/deck-texts/pauper/7704072.json",
      "message": "Reused existing published deck-text blob."
    },
    {
      "scope": "deck-text",
      "status": "skipped",
      "format": "pauper",
      "deck_id": "7704073",
      "path": "archive/deck-texts/pauper/7704073.json",
      "message": "Reused existing published deck-text blob."
    },
    {
      "scope": "deck-text",
      "status": "skipped",
      "format": "pauper",
      "deck_id": "7704074",
      "path": "archive/deck-texts/pauper/7704074.json",
      "message": "Reused existing published deck-text blob."
    },
    {
      "scope": "deck-text",
      "status": "skipped",
      "format": "pauper",
      "deck_id": "7704075",
      "path": "archive/deck-texts/pauper/7704075.json",
      "message": "Reused existing published deck-text blob."
    },
    {
      "scope": "deck-text",
      "status": "skipped",
      "format": "pauper",
      "deck_id": "7704076",
      "path": "archive/deck-texts/pauper/7704076.json",
      "message": "Reused existing published deck-text blob."
    },
    {
      "scope": "deck-text",
      "status": "skipped",
      "format": "pauper",
      "deck_id": "7704077",
      "path": "archive/deck-texts/pauper/7704077.json",
      "message": "Reused existing published deck-text blob."
    },
    {
      "scope": "deck-text",
      "status": "skipped",
      "format": "pauper",
      "deck_id": "7704078",
      "path": "archive/deck-texts/pauper/7704078.json",
      "message": "Reused existing published deck-text blob."
    },
    {
      "scope": "deck-text",
      "status": "skipped",
      "format": "pauper",
      "deck_id": "7704079",
      "path": "archive/deck-texts/pauper/7704079.json",
      "message": "Reused existing published deck-text blob."
    },
    {
      "scope": "deck-text",
      "status": "skipped",
      "format": "pauper",
      "deck_id": "7704080",
      "path": "archive/deck-texts/pauper/7704080.json",
      "message": "Reused existing published deck-text blob."
    },
    {
      "scope": "deck-text",
      "status": "skipped",
      "format": "pauper",
      "deck_id": "7704081",
      "path": "archive/deck-texts/pauper/7704081.json",
      "message": "Reused existing published deck-text blob."
    },
    {
      "scope": "deck-text",
      "status": "skipped",
      "format": "pauper",
      "deck_id": "7704082",
      "path": "archive/deck-texts/pauper/7704082.json",
      "message": "Reused existing published deck-text blob."
    },
    {
      "scope": "deck-text",
      "status": "skipped",
      "format": "pauper",
      "deck_id": "7704083",
      "path": "archive/deck-texts/pauper/7704083.json",
      "message": "Reused existing published deck-text blob."
    },
    {
      "scope": "deck-text",
      "status": "skipped",
      "format": "pauper",
      "deck_id": "7704084",
      "path": "archive/deck-texts/pauper/7704084.json",
      "message": "Reused existing published deck-text blob."
    },
    {
      "scope": "deck-text",
      "status": "skipped",
      "format": "pauper",
      "deck_id": "7704085",
      "path": "archive/deck-texts/pauper/7704085.json",
      "message": "Reused existing published deck-text blob."
    },
    {
      "scope": "deck-text",
      "status": "skipped",
      "format": "pauper",
      "deck_id": "7704092",
      "path": "archive/deck-texts/pauper/7704092.json",
      "message": "Reused existing published deck-text blob."
    },
    {
      "scope": "deck-text",
      "status": "skipped",
      "format": "pauper",
      "deck_id": "7704164",
      "path": "archive/deck-texts/pauper/7704164.json",
      "message": "Reused existing published deck-text blob."
    },
    {
      "scope": "deck-text",
      "status": "skipped",
      "format": "pauper",
      "deck_id": "7704165",
      "path": "archive/deck-texts/pauper/7704165.json",
      "message": "Reused existing published deck-text blob."
    },
    {
      "scope": "deck-text",
      "status": "skipped",
      "format": "pauper",
      "deck_id": "7704257",
      "path": "archive/deck-texts/pauper/7704257.json",
      "message": "Reused existing published deck-text blob."
    },
    {
      "scope": "deck-text",
      "status": "skipped",
      "format": "pauper",
      "deck_id": "7704316",
      "path": "archive/deck-texts/pauper/7704316.json",
      "message": "Reused existing published deck-text blob."
    },
    {
      "scope": "deck-text",
      "status": "skipped",
      "format": "pauper",
      "deck_id": "7704317",
      "path": "archive/deck-texts/pauper/7704317.json",
      "message": "Reused existing published deck-text blob."
    },
    {
      "scope": "deck-text",
      "status": "skipped",
      "format": "pauper",
      "deck_id": "7704417",
      "path": "archive/deck-texts/pauper/7704417.json",
      "message": "Reused existing published deck-text blob."
    }
  ]
}